{"skeleton":{"hash":"jDIaZ1G7xgPlooH5dLXf7rj9eNA","spine":"2.1.27","width":118.15,"height":105.18,"images":""},"bones":[{"name":"root"},{"name":"bone","parent":"root","x":5.66,"y":-8.31},{"name":"bone2","parent":"bone","length":22.49,"x":2.26,"y":-10.93,"rotation":110.3},{"name":"bone3","parent":"bone2","length":14.19,"x":18.8,"y":11.47,"scaleX":0.926,"rotation":58.72},{"name":"bone4","parent":"bone2","length":12.46,"x":2.59,"y":8.97,"rotation":158.51},{"name":"bone5","parent":"bone2","length":10.5,"x":16.01,"y":-8.73,"rotation":-88.19},{"name":"bone6","parent":"bone2","length":11.03,"x":-1.38,"y":-11.72,"rotation":-124.41},{"name":"bone7","parent":"bone2","length":45.35,"x":20.71,"y":-4.01,"rotation":-5.84},{"name":"bone8","parent":"bone2","length":19.5,"x":6.94,"y":14.81,"rotation":80.61},{"name":"bone10","parent":"bone5","length":20.33,"x":13.63,"y":-0.65,"rotation":35.02},{"name":"bone11","parent":"bone7","length":21.06,"x":5.65,"y":-25.89,"rotation":3.6},{"name":"bone12","parent":"bone7","length":11.88,"x":12.46,"y":-12.29,"rotation":-3.6},{"name":"bone9","parent":"bone8","length":20.18,"x":19.5,"y":-0.13,"rotation":-32.17},{"name":"bone13","parent":"bone10","length":15.5,"x":33.93,"y":-25.59,"rotation":28.86}],"slots":[{"name":"common_squirrel_earth_head_2","bone":"bone11","attachment":"common_squirrel_earth_head_02"},{"name":"bone10","bone":"bone10","attachment":"common_squirrel_earth_weapon_01"},{"name":"common_squirrel_earth_tail_2","bone":"bone8","attachment":"common_squirrel_earth_tail_01"},{"name":"common_squirrel_earth_tail_1","bone":"bone8"},{"name":"common_squirrel_earth_arm_4","bone":"bone5","attachment":"common_squirrel_earth_arm_02"},{"name":"common_squirrel_earth_arm_2","bone":"bone5"},{"name":"common_squirrel_earth_leg_4","bone":"bone6","attachment":"common_squirrel_earth_leg_02"},{"name":"common_squirrel_earth_leg_2","bone":"bone6"},{"name":"common_squirrel_earth_body_2","bone":"bone2","attachment":"common_squirrel_earth_body_01"},{"name":"common_squirrel_earth_body_1","bone":"bone2"},{"name":"common_squirrel_earth_body_01","bone":"root"},{"name":"common_squirrel_earth_leg_3","bone":"bone4"},{"name":"common_squirrel_earth_leg_1","bone":"bone4"},{"name":"bone8","bone":"bone7","attachment":"common_squirrel_earth_head_01"},{"name":"common_squirrel_earth_acc_01","bone":"bone12","attachment":"common_squirrel_earth_acc_01"},{"name":"common_squirrel_earth_head_1","bone":"bone7"},{"name":"common_squirrel_earth_arm_3","bone":"bone3","attachment":"common_squirrel_earth_arm_01"},{"name":"common_squirrel_earth_arm_1","bone":"bone3"},{"name":"common_squirrel_earth_arm_01","bone":"root"},{"name":"bone7","bone":"bone7"},{"name":"bone4","bone":"bone4","attachment":"common_squirrel_earth_leg_01"},{"name":"common_squirrel_earth_leg_01","bone":"root"},{"name":"common_squirrel_earth_acc_2","bone":"bone10","attachment":"common_squirrel_earth_acc_02"},{"name":"common_squirrel_earth_arm_5","bone":"bone3","color":"ffffff00","attachment":"common_squirrel_earth_arm_02"}],"skins":{"default":{"bone10":{"common_squirrel_earth_weapon_01":{"x":20.72,"y":-3.05,"rotation":-57.13,"width":45,"height":52}},"bone4":{"common_squirrel_earth_leg_01":{"x":7.77,"y":-0.01,"rotation":91.18,"width":34,"height":34}},"bone8":{"common_squirrel_earth_head_01":{"type":"mesh","uvs":[0.18259,0.14611,0.12186,0.24401,0.12376,0.34958,0.18828,0.42636,0.16551,0.52042,0.10099,0.51082,0,0.51274,0,0.61832,0.04975,0.67974,0.15412,0.76612,0.26419,0.7834,0.37805,0.75269,0.49192,0.80835,0.60388,0.81795,0.71965,0.81219,0.78098,0.79215,0.843,0.77188,0.87905,0.70278,0.90942,0.6759,0.93029,0.58761,0.91321,0.55113,0.9284,0.44556,0.90183,0.32271,0.91511,0.22289,0.87336,0.1154,0.73293,0.06549,0.72534,0.11924,0.58111,0.10964,0.54357,0.11369,0.43878,0.125,0.30404,0.20562,0.24332,0.17682,0.22434,0.13843,0.21106,0.59336,0.27368,0.61448,0.35149,0.63559,0.47294,0.64519,0.07632,0.56457,0.12945,0.61832,0.21295,0.66055,0.30784,0.67399,0.70417,0.27088,0.79337,0.41677,0.79337,0.52618,0.83322,0.58761,0.82373,0.67207,0.29806,0.43212,0.27719,0.51658,0.35879,0.44172,0.41382,0.40141,0.42331,0.32079,0.36638,0.27664,0.20887,0.28048,0.24872,0.36494],"triangles":[26,25,24,41,27,26,28,27,41,51,30,29,31,52,0,31,0,32,52,31,30,1,0,52,50,51,29,24,23,26,2,1,52,51,53,52,51,52,30,2,52,53,49,51,50,53,51,49,26,23,41,22,42,23,42,41,23,3,2,53,46,53,49,3,53,46,48,46,49,42,22,21,47,3,46,4,3,47,50,41,49,43,42,21,20,43,21,37,6,5,44,43,20,33,4,47,47,46,48,34,33,47,4,37,5,38,4,33,38,37,4,7,6,37,35,47,48,34,47,35,50,29,28,41,50,28,49,41,42,43,36,42,36,49,42,48,49,36,35,48,36,39,33,34,38,33,39,45,43,44,36,43,45,44,20,19,40,34,35,39,34,40,18,44,19,45,44,18,8,7,37,8,37,38,17,45,18,11,35,36,40,35,11,9,38,39,8,38,9,16,45,17,10,39,40,10,40,11,9,39,10,45,14,36,15,45,16,36,13,12,11,36,12,45,15,14,14,13,36],"vertices":[61.54,30.92,54.63,38.22,45.69,40.34999,37.81,36.52,30.38,40.5,32.61,45.79,34.66,54.44,25.77,56.73,19.5,53.83,9.93,46.81,6.06,37.8,6.15,27.43,-1.03,18.94,-4.3,9.6,-6.35,-0.38,-6.01,-6.04,-5.67,-11.76,-0.64,-16.34,0.95,-19.51,7.93,-23.2,11.38,-22.54,19.94,-26.12,30.87,-26.53,38.99,-29.82,48.97,-28.6,56.25,-17.71999,51.89,-15.9,55.87,-3.82,56.35,-0.52999,57.7,8.63,53.86,21.86,57.62,26.41,61.27,27.2,23.24,38.2,20.08,33.33,16.6,27.15,13.12,17.01,28.62,49.06,22.93,45.7,17.54,39.5,14.32,31.71,39.58,-10.81,25.33,-15.24,16.11,-12.87,10.06,-14.93,3.16,-12.29,34.91,27.29,28.25,30.9,32.77,22.32,34.96,16.76,41.54,14.2,46.51,18.09,49.65,31.6,41.66,30.04],"hull":33,"edges":[0,2,2,4,4,6,6,8,8,10,10,12,12,14,14,16,16,18,18,20,20,22,22,24,24,26,26,28,32,34,34,36,36,38,38,40,40,42,42,44,44,46,46,48,48,50,50,52,52,54,58,60,60,62,62,64,0,64,8,66,66,68,68,70,70,72,72,22,10,74,74,16,8,76,76,18,66,78,78,20,68,80,80,22,54,56,56,58,56,82,82,84,84,86,86,88,88,90,28,30,30,32,90,30,92,94,94,68,92,96,6,92,96,98,98,100,100,102,102,60,0,104,104,106,106,98],"width":88,"height":87}},"common_squirrel_earth_acc_01":{"common_squirrel_earth_acc_01":{"x":6.03,"y":9.14,"rotation":-100.85,"width":53,"height":39}},"common_squirrel_earth_acc_2":{"common_squirrel_earth_acc_02":{"type":"mesh","uvs":[1,0.51131,1,1,0.4473,1,0,1,0,0.47106,0,0,0.46973,0,1,0,0.55384,0.49521],"triangles":[4,5,6,8,6,7,4,6,8,8,7,0,2,3,4,8,2,4,8,0,1,2,8,1],"vertices":[26.52,-18.75,10.51,-29.09,2.10999,-16.09,-4.67999,-5.57,12.64,5.61,28.07,15.58,35.21,4.53,43.27,-7.93,20.26,-7.92],"hull":8,"edges":[10,12,12,14,6,8,8,10,2,4,4,6,2,0,0,14],"width":28,"height":39}},"common_squirrel_earth_arm_3":{"common_squirrel_earth_arm_01":{"x":6.96,"y":1.26,"scaleX":1.079,"rotation":-164.77,"width":33,"height":25}},"common_squirrel_earth_arm_4":{"common_squirrel_earth_arm_02":{"x":6.38,"y":-0.88,"rotation":-22.11,"width":25,"height":17}},"common_squirrel_earth_arm_5":{"common_squirrel_earth_arm_02":{"x":5.22,"y":0.88,"scaleX":1.079,"rotation":-23.14,"width":25,"height":17}},"common_squirrel_earth_body_2":{"common_squirrel_earth_body_01":{"type":"mesh","uvs":[1,1,0,1,0,0,1,0,0.60266,0.84799,0.37064,0.66026,0.35653,0.44962,0.41344,0.30028,0.65034,0.18163,0.77343,0.33486,0.64074,0.44205,0.65013,0.63354,0.78269,0.78294],"triangles":[8,2,3,7,2,8,9,8,3,10,7,8,10,8,9,6,2,7,6,7,10,11,10,9,11,5,6,11,6,10,0,12,9,11,9,12,4,5,11,4,11,12,1,2,6,1,6,5,0,9,3,4,12,0,1,5,4,1,4,0],"vertices":[-19.18,-7.21,-6,28.43,38.07,12.13,24.9,-23.5,-7.24,4.46999,4.08,9.68,13.55,6.75,19.39,2.29,21.5,-8.08,13.12,-9.97,10.14,-3.5,1.58,-0.71,-6.75,-3],"hull":4,"edges":[0,2,2,4,4,6,0,6,8,10,10,12,12,14,14,16,18,20,20,22,22,24],"width":38,"height":47}},"common_squirrel_earth_head_2":{"common_squirrel_earth_head_02":{"x":4.47,"y":0.57,"rotation":-108.06,"width":47,"height":33}},"common_squirrel_earth_leg_4":{"common_squirrel_earth_leg_02":{"x":6.72,"y":-0.38,"rotation":14.1,"width":29,"height":29}},"common_squirrel_earth_tail_2":{"common_squirrel_earth_tail_01":{"type":"skinnedmesh","uvs":[0.83411,0.25918,0.75624,0.28963,0.67295,0.25309,0.58965,0.18304,0.51178,0.11299,0.41038,0.07036,0.31259,0.0734,0.20938,0.12213,0.1297,0.20131,0.07719,0.32009,0.06632,0.47845,0.09168,0.6429,0.15143,0.75863,0.21662,0.83781,0.29992,0.91699,0.37959,0.93831,0.47376,0.94136,0.55343,0.93222,0.64397,0.89263,0.71641,0.84086,0.78703,0.75254,0.85222,0.65813,0.89386,0.56981,0.91922,0.46627,0.92465,0.3414,0.87938,0.28049],"triangles":[13,16,15,13,18,16,13,15,14,12,19,13,3,11,7,7,4,3,7,6,4,6,5,4,11,2,12,9,8,7,7,11,10,9,7,10,18,17,16,18,13,19,21,20,2,2,20,19,2,19,12,3,2,11,21,2,1,21,1,22,23,22,0,0,22,1,24,23,0,24,0,25],"vertices":[1,8,-8.88,-10.22,1,2,8,-2.97,-9.99,0.99758,12,-13.77,-20.32,0.00241,2,8,2.77,-12.74,0.94245,12,-7.44,-19.58,0.05754,2,8,8.24,-16.93,0.72218,12,-0.58,-20.21999,0.27781,2,8,13.31,-21.05,0.44663,12,5.9,-21,0.55336,2,8,20.33,-24.31,0.1947,12,13.57,-20.03,0.80529,2,8,27.46,-25.55,0.06211,12,20.26,-17.28,0.93788,2,8,35.36,-24.89,0.00656,12,26.61,-12.51,0.99343,1,12,30.84,-7.13,1,1,12,32.56,-0.85,1,1,12,30.79,5.93,1,1,12,26.41,11.99,1,1,12,20.45,15.13,1,2,8,40.8,6.12,0.00441,12,14.69,16.62999,0.99558,2,8,35.4,10.71,0.0529,12,7.68,17.64,0.94709,2,8,29.79,12.75,0.17346,12,1.85,16.37999,0.82653,2,8,22.98,14.2,0.45297,12,-4.69,13.98,0.54702,2,8,17.11,14.92,0.71384,12,-10.04,11.47,0.28615,2,8,10.2,14.48,0.91833,12,-15.65,7.41,0.08166,2,8,4.51,13.25,0.98551,12,-19.82,3.35,0.01448,1,8,-1.35,10.43,1,1,8,-6.87,7.26,1,1,8,-10.63,4.03,1,1,8,-13.34,-0.08,1,1,8,-14.77,-5.4,1,1,8,-11.99,-8.66,1],"hull":26,"edges":[0,2,2,4,4,6,6,8,8,10,10,12,12,14,14,16,16,18,18,20,20,22,22,24,24,26,26,28,28,30,30,32,32,34,34,36,36,38,38,40,40,42,42,44,44,46,46,48,48,50,0,50],"width":74,"height":44}}}},"events":{"attack":{}},"animations":{"attack":{"slots":{"common_squirrel_earth_acc_2":{"attachment":[{"time":0,"name":"common_squirrel_earth_acc_02"},{"time":1,"name":"common_squirrel_earth_acc_02"}],"color":[{"time":0,"color":"ffffffff","curve":"stepped"},{"time":1,"color":"ffffffff"}]}},"bones":{"bone":{"rotate":[{"time":0,"angle":-12},{"time":0.3333,"angle":0},{"time":0.5333,"angle":8,"curve":"stepped"},{"time":0.6666,"angle":8},{"time":1,"angle":-12}],"translate":[{"time":0,"x":0,"y":0},{"time":0.3333,"x":0,"y":16.74},{"time":0.4333,"x":-12.67,"y":14.23},{"time":0.5,"x":-27.41,"y":12.55},{"time":0.5333,"x":-29.58,"y":11.71,"curve":"stepped"},{"time":0.6666,"x":-29.58,"y":11.71},{"time":1,"x":0,"y":0}],"scale":[{"time":0,"x":1,"y":1},{"time":0.3333,"x":1.055,"y":1.065},{"time":0.4333,"x":1.265,"y":1.2},{"time":0.5,"x":1.2,"y":1.2,"curve":"stepped"},{"time":0.5333,"x":1.2,"y":1.2,"curve":"stepped"},{"time":0.6666,"x":1.2,"y":1.2},{"time":0.7,"x":1.31,"y":1.251},{"time":0.7333,"x":1,"y":1,"curve":"stepped"},{"time":1,"x":1,"y":1}]},"bone9":{"rotate":[{"time":0,"angle":0},{"time":0.3333,"angle":-19.36},{"time":0.4666,"angle":-29.24},{"time":0.7,"angle":29.23},{"time":1,"angle":0}],"translate":[{"time":0,"x":0,"y":0,"curve":"stepped"},{"time":0.3333,"x":0,"y":0,"curve":"stepped"},{"time":1,"x":0,"y":0}],"scale":[{"time":0,"x":1,"y":1,"curve":"stepped"},{"time":0.3333,"x":1,"y":1,"curve":"stepped"},{"time":1,"x":1,"y":1}]},"bone8":{"rotate":[{"time":0,"angle":-24.45},{"time":0.1333,"angle":-31.96},{"time":0.3666,"angle":-31.74},{"time":0.4666,"angle":-17.62},{"time":0.5333,"angle":-33.72},{"time":0.6666,"angle":2.02},{"time":0.7,"angle":20.39},{"time":1,"angle":-24.45}],"translate":[{"time":0,"x":0,"y":0,"curve":"stepped"},{"time":0.3666,"x":0,"y":0,"curve":"stepped"},{"time":1,"x":0,"y":0}],"scale":[{"time":0,"x":1,"y":1,"curve":"stepped"},{"time":0.3666,"x":1,"y":1},{"time":0.5333,"x":1.089,"y":1.126},{"time":1,"x":1,"y":1}]},"bone11":{"rotate":[{"time":0,"angle":0,"curve":"stepped"},{"time":0.3666,"angle":0,"curve":"stepped"},{"time":1,"angle":0}],"translate":[{"time":0,"x":0,"y":0,"curve":"stepped"},{"time":0.3666,"x":0,"y":0,"curve":"stepped"},{"time":1,"x":0,"y":0}],"scale":[{"time":0,"x":1,"y":1,"curve":"stepped"},{"time":0.3666,"x":1,"y":1,"curve":"stepped"},{"time":1,"x":1,"y":1}]},"bone7":{"rotate":[{"time":0,"angle":5.89},{"time":0.2666,"angle":5.75},{"time":0.3666,"angle":12.56},{"time":0.4333,"angle":8.14},{"time":0.7,"angle":0},{"time":0.8,"angle":-11.17},{"time":1,"angle":5.89}],"translate":[{"time":0,"x":-2.28,"y":0.44},{"time":0.3666,"x":0,"y":0},{"time":0.4333,"x":-2.31,"y":1.31},{"time":0.7,"x":-1.01,"y":2.7},{"time":0.8,"x":-4.55,"y":2.35},{"time":1,"x":-2.28,"y":0.44}],"scale":[{"time":0,"x":1,"y":1,"curve":"stepped"},{"time":0.3666,"x":1,"y":1},{"time":0.7,"x":1,"y":1.025},{"time":1,"x":1,"y":1}]},"bone6":{"rotate":[{"time":0,"angle":298.58},{"time":0.3666,"angle":263.72},{"time":0.4333,"angle":20.92},{"time":0.5,"angle":22.24},{"time":0.6666,"angle":30.09},{"time":1,"angle":298.58}],"translate":[{"time":0,"x":-1.24,"y":6.18},{"time":0.3666,"x":-2.56,"y":0.96},{"time":0.4333,"x":1.5,"y":0.57},{"time":0.5,"x":0.07,"y":3.77},{"time":0.6333,"x":2.38,"y":6.61},{"time":1,"x":-1.24,"y":6.18}],"scale":[{"time":0,"x":1,"y":1},{"time":0.3666,"x":1,"y":0.914},{"time":1,"x":1,"y":1}]},"bone10":{"rotate":[{"time":0,"angle":27.33},{"time":0.3666,"angle":35.93},{"time":0.5,"angle":41.84},{"time":0.6333,"angle":29.87},{"time":0.6666,"angle":20.71},{"time":0.7,"angle":-1.2},{"time":1,"angle":27.33}],"translate":[{"time":0,"x":0,"y":0,"curve":"stepped"},{"time":0.3666,"x":0,"y":0},{"time":0.5,"x":5.04,"y":-2.09},{"time":0.6333,"x":0,"y":0,"curve":"stepped"},{"time":1,"x":0,"y":0}],"scale":[{"time":0,"x":1,"y":1,"curve":"stepped"},{"time":0.3666,"x":1,"y":1,"curve":"stepped"},{"time":0.6333,"x":1,"y":1,"curve":"stepped"},{"time":1,"x":1,"y":1}]},"bone5":{"rotate":[{"time":0,"angle":-26.1},{"time":0.1333,"angle":1.94},{"time":0.3666,"angle":3.15},{"time":0.8333,"angle":-16.45},{"time":1,"angle":-26.1}],"translate":[{"time":0,"x":-2.94,"y":2.23},{"time":0.3666,"x":0,"y":0},{"time":0.5,"x":-0.38,"y":4.6},{"time":0.6333,"x":-0.53,"y":8.92},{"time":1,"x":-2.94,"y":2.23}],"scale":[{"time":0,"x":1,"y":1},{"time":0.3666,"x":1.097,"y":1},{"time":0.4333,"x":1.215,"y":1},{"time":0.5,"x":1.276,"y":1},{"time":1,"x":1,"y":1}]},"bone4":{"rotate":[{"time":0,"angle":0},{"time":0.3666,"angle":-18.29},{"time":0.4333,"angle":-315.21},{"time":0.5,"angle":-323.4},{"time":0.6333,"angle":-334.89},{"time":0.6666,"angle":-318.62,"curve":"stepped"},{"time":0.7,"angle":-318.62},{"time":1,"angle":0}],"translate":[{"time":0,"x":0,"y":0,"curve":"stepped"},{"time":0.3666,"x":0,"y":0},{"time":0.4333,"x":1.5,"y":0.86},{"time":0.5,"x":1.89,"y":4.09},{"time":0.6333,"x":2.57,"y":7.03},{"time":0.6666,"x":3.95,"y":6.07,"curve":"stepped"},{"time":0.7,"x":3.95,"y":6.07},{"time":1,"x":0,"y":0}],"scale":[{"time":0,"x":1,"y":1,"curve":"stepped"},{"time":0.3666,"x":1,"y":1,"curve":"stepped"},{"time":1,"x":1,"y":1}]},"bone3":{"rotate":[{"time":0,"angle":46.12},{"time":0.1333,"angle":-19.71},{"time":0.3666,"angle":-41.46,"curve":"stepped"},{"time":0.4333,"angle":-41.46,"curve":"stepped"},{"time":0.5,"angle":-41.46},{"time":0.6333,"angle":-41.37},{"time":0.6666,"angle":-43.33},{"time":0.7333,"angle":16.29},{"time":1,"angle":46.12}],"translate":[{"time":0,"x":-1.74,"y":1.33},{"time":0.3666,"x":-0.07,"y":0.3},{"time":0.4333,"x":-1.9,"y":3.38},{"time":0.4666,"x":-2.92,"y":11.2},{"time":0.5,"x":-3.74,"y":10.28},{"time":0.6333,"x":-0.89,"y":12.8},{"time":0.6666,"x":-0.06,"y":3.94},{"time":1,"x":-1.74,"y":1.33}],"scale":[{"time":0,"x":1,"y":1,"curve":"stepped"},{"time":0.3666,"x":1,"y":1},{"time":0.4333,"x":0.954,"y":1.038,"curve":"stepped"},{"time":0.5,"x":0.954,"y":1.038},{"time":1,"x":1,"y":1}],"flipX":[{"time":0.3666,"x":true},{"time":0.4333,"x":true},{"time":0.5,"x":true},{"time":0.6666}]},"bone2":{"rotate":[{"time":0,"angle":0},{"time":0.3666,"angle":7.85},{"time":1,"angle":0}],"translate":[{"time":0,"x":0,"y":0,"curve":"stepped"},{"time":0.3666,"x":0,"y":0,"curve":"stepped"},{"time":1,"x":0,"y":0}],"scale":[{"time":0,"x":1,"y":1},{"time":0.3666,"x":1.016,"y":1},{"time":1,"x":1,"y":1}]},"bone13":{"translate":[{"time":0.7,"x":-7.59,"y":1.81}]},"bone12":{"translate":[{"time":0,"x":0,"y":0,"curve":"stepped"},{"time":1,"x":0,"y":0}]}},"ffd":{"default":{"bone8":{"common_squirrel_earth_head_01":[{"time":0},{"time":0.7,"vertices":[-0.77456,-2.38382,0,0,-0.53345,-2.10213,-1.93898,-3.63051,-6.51472,-2.94734,-7.96143,0.70921,-8.36663,-0.2193,-13.83636,2.95898,-14.07092,-1.30962,-8.42302,-2.44661,-4.18587,-0.45391,-3.16499,-2.44648,0,0,0,0,0,0,0.73864,2.91063,0,0,0,0,0,0,0,0,0,0,0,0,0,0,0,0,-0.64117,-0.52161,-1.33364,-2.58204,-1.2722,0.3338,0,0,-0.0308,1.21537,-1.5441,1.26748,-1.13357,-2.46207,-1.14384,-3.83916,-0.85657,-2.70725,-2.90332,-4.75724,-2.26214,-4.23563,-2.30827,-5.08585,0,0,-14.17356,0.95942,-13.09705,-3.44258,-9.16163,-5.35727,-7.0841,-4.52263,-0.26677,1.65386,0.17949,2.74405,-0.3027,2.18862,-0.14368,2.10733,0.21029,1.49705,-1.23627,-0.19302,-0.4924,-1.94044,-1.0054,-1.28841,-0.24621,-0.97022,0,0,0.15903,-0.04172,-0.5847,-3.64092,-0.06659,-3.60439]},{"time":1}]},"common_squirrel_earth_acc_2":{"common_squirrel_earth_acc_02":[{"time":0},{"time":0.1333,"offset":2,"vertices":[2.13186,-2.79618,0,0,2.79045,-5.29475,0,0,1.17704,-1.77316]},{"time":0.2666,"offset":2,"vertices":[-13.08407,2.67883,0,0,-3.60275,3.61308,0,0,2.40497,-2.88912,0,0,3.19163,-5.05486]},{"time":0.3666,"offset":2,"vertices":[2.06809,-1.2208,0,0,-4.76879,9.38401]},{"time":0.4,"vertices":[-4.97011,-3.98779,-23.02054,56.23091,-5.13574,49.29616,-4.1476,34.12561,1.3124,13.04853,6.89338,-9.23008,2.09618,-17.2227,-4.27523,-26.26187,1.48223,5.68056],"curve":"stepped"},{"time":0.4333,"vertices":[-4.97011,-3.98779,-23.02054,56.23091,-5.13574,49.29616,-4.1476,34.12561,1.3124,13.04853,6.89338,-9.23008,2.09618,-17.2227,-4.27523,-26.26187,1.48223,5.68056]},{"time":0.4666,"vertices":[3.73838,-8.18359,-24.14377,56.97543,-12.0761,57.63202,-1.54671,57.83513,-1.94175,22.91228,5.98918,-10.9389,2.77148,-16.15933,-5.74559,-14.68112,-6.82945,13.88305]},{"time":0.5,"vertices":[3.73838,-8.18359,-18.86019,63.26539,-8.06636,64.83012,0.27659,64.90854,-0.4088,22.17381,5.98918,-10.9389,2.77148,-16.15933,-5.74559,-14.68112,-8.43195,19.36734]},{"time":0.6,"vertices":[3.73838,-8.18359,-24.14377,56.97543,-12.0761,57.63202,-1.54671,57.83513,-1.94175,22.91228,5.98918,-10.9389,2.77148,-16.15933,-5.74559,-14.68112,-6.82945,13.88305],"curve":"stepped"},{"time":0.6333,"vertices":[3.73838,-8.18359,-24.14377,56.97543,-12.0761,57.63202,-1.54671,57.83513,-1.94175,22.91228,5.98918,-10.9389,2.77148,-16.15933,-5.74559,-14.68112,-6.82945,13.88305]},{"time":0.6666,"vertices":[9.15274,7.13841,18.25534,-10.36053,13.69048,-22.02871,14.63119,-14.76921,4.16687,-2.01988,-5.52802,2.09409,0,0,-7.65788,7.46868,2.19486,-4.46208]},{"time":0.7,"vertices":[6.143,2.51156,23.45043,-6.54357,11.81361,-16.01129,12.80875,-9.9515,2.90139,-0.32357,-0.05163,1.77627,0,0,-9.35685,0.76662,1.48454,0.58204]},{"time":0.7666,"offset":2,"vertices":[-11.89387,-4.90093,0,0,7.28874,11.36113,0,0,-4.77721,-1.61503,0,0,-0.78446,-7.54185]},{"time":0.8,"offset":2,"vertices":[-18.23805,8.31482,-7.62221,11.24418,6.24749,9.73811,0.62573,1.41313,1.73373,-7.62493,0,0,-0.67239,-6.46444,-4.50867,1.19982]},{"time":0.8333,"offset":2,"vertices":[5.03429,-4.76171,0,0,5.20624,8.11509,0,0,0.92333,-7.53172,0,0,-0.56033,-5.38703]},{"time":0.8666,"vertices":[3.9783,6.18286,12.86996,-10.17544,3.41931,-4.26989,4.16499,6.49207,0,0,0.73866,-6.02537,0,0,-0.44826,-4.30962,1.82278,-0.47772]},{"time":1}]},"common_squirrel_earth_body_2":{"common_squirrel_earth_body_01":[{"time":0,"offset":4,"vertices":[-1.16438,-2.19264,0.31402,2.14815]},{"time":0.4333},{"time":0.5,"vertices":[-1.3317,3.92671,-1.3317,3.92671,-1.3317,3.92671,-1.3317,3.92671]},{"time":0.6333,"vertices":[1.34858,6.71934,1.34858,6.71934,1.34858,6.71934,1.34858,6.71934]},{"time":1,"offset":4,"vertices":[-1.16438,-2.19264,0.31402,2.14815]}]}}},"drawOrder":[{"time":0,"offsets":[{"slot":"common_squirrel_earth_acc_2","offset":-5}]},{"time":0.7,"offsets":[{"slot":"bone10","offset":17}]},{"time":1,"offsets":[{"slot":"common_squirrel_earth_acc_2","offset":-5}]}],"events":[{"time":0.7,"name":"attack","string":"40,60"}]},"die_appear":{"slots":{"bone4":{"attachment":[{"time":0,"name":"common_squirrel_earth_leg_01"},{"time":0.6666,"name":"common_squirrel_earth_leg_01"}]},"bone7":{"attachment":[{"time":0,"name":null},{"time":0.6666,"name":null}]},"bone8":{"attachment":[{"time":0,"name":"common_squirrel_earth_head_01"},{"time":0.6666,"name":"common_squirrel_earth_head_01"}]},"bone10":{"attachment":[{"time":0,"name":"common_squirrel_earth_weapon_01"},{"time":0.6666,"name":"common_squirrel_earth_weapon_01"}]},"common_squirrel_earth_acc_01":{"attachment":[{"time":0,"name":"common_squirrel_earth_acc_01"},{"time":0.6666,"name":"common_squirrel_earth_acc_01"}]},"common_squirrel_earth_acc_2":{"attachment":[{"time":0,"name":"common_squirrel_earth_acc_02"},{"time":0.6666,"name":"common_squirrel_earth_acc_02"}],"color":[{"time":0,"color":"ffffffff","curve":"stepped"},{"time":0.6666,"color":"ffffffff"}]},"common_squirrel_earth_arm_01":{"attachment":[{"time":0,"name":null},{"time":0.6666,"name":null}]},"common_squirrel_earth_arm_1":{"attachment":[{"time":0,"name":null},{"time":0.6666,"name":null}]},"common_squirrel_earth_arm_2":{"attachment":[{"time":0,"name":null},{"time":0.6666,"name":null}]},"common_squirrel_earth_arm_3":{"attachment":[{"time":0,"name":"common_squirrel_earth_arm_01"},{"time":0.6666,"name":"common_squirrel_earth_arm_01"}],"color":[{"time":0,"color":"ffffffff","curve":[0.25,0,0.75,1]},{"time":0.3333,"color":"ffffff00","curve":"stepped"},{"time":0.6666,"color":"ffffff00"}]},"common_squirrel_earth_arm_4":{"attachment":[{"time":0,"name":"common_squirrel_earth_arm_02"},{"time":0.6666,"name":"common_squirrel_earth_arm_02"}]},"common_squirrel_earth_arm_5":{"attachment":[{"time":0,"name":"common_squirrel_earth_arm_02"},{"time":0.6666,"name":"common_squirrel_earth_arm_02"}],"color":[{"time":0,"color":"ffffff00","curve":[0.25,0,0.75,1]},{"time":0.3333,"color":"ffffffff","curve":"stepped"},{"time":0.6666,"color":"ffffffff"}]},"common_squirrel_earth_body_01":{"attachment":[{"time":0,"name":null},{"time":0.6666,"name":null}]},"common_squirrel_earth_body_1":{"attachment":[{"time":0,"name":null},{"time":0.6666,"name":null}]},"common_squirrel_earth_body_2":{"attachment":[{"time":0,"name":"common_squirrel_earth_body_01"},{"time":0.6666,"name":"common_squirrel_earth_body_01"}]},"common_squirrel_earth_head_1":{"attachment":[{"time":0,"name":null},{"time":0.6666,"name":null}]},"common_squirrel_earth_head_2":{"attachment":[{"time":0,"name":"common_squirrel_earth_head_02"},{"time":0.6666,"name":"common_squirrel_earth_head_02"}]},"common_squirrel_earth_leg_01":{"attachment":[{"time":0,"name":null},{"time":0.6666,"name":null}]},"common_squirrel_earth_leg_1":{"attachment":[{"time":0,"name":null},{"time":0.6666,"name":null}]},"common_squirrel_earth_leg_2":{"attachment":[{"time":0,"name":null},{"time":0.6666,"name":null}]},"common_squirrel_earth_leg_3":{"attachment":[{"time":0,"name":null},{"time":0.6666,"name":null}]},"common_squirrel_earth_leg_4":{"attachment":[{"time":0,"name":"common_squirrel_earth_leg_02"},{"time":0.6666,"name":"common_squirrel_earth_leg_02"}]},"common_squirrel_earth_tail_1":{"attachment":[{"time":0,"name":null},{"time":0.6666,"name":null}]},"common_squirrel_earth_tail_2":{"attachment":[{"time":0,"name":"common_squirrel_earth_tail_01"},{"time":0.6666,"name":"common_squirrel_earth_tail_01"}]}},"bones":{"root":{"rotate":[{"time":0,"angle":0,"curve":"stepped"},{"time":0.3333,"angle":0,"curve":"stepped"},{"time":0.6666,"angle":0}],"translate":[{"time":0,"x":0,"y":0,"curve":"stepped"},{"time":0.3333,"x":0,"y":0,"curve":"stepped"},{"time":0.6666,"x":0,"y":0}],"scale":[{"time":0,"x":1,"y":1,"curve":"stepped"},{"time":0.3333,"x":1,"y":1,"curve":"stepped"},{"time":0.6666,"x":1,"y":1}]},"bone9":{"rotate":[{"time":0,"angle":0,"curve":"stepped"},{"time":0.3333,"angle":0,"curve":"stepped"},{"time":0.6666,"angle":0}],"translate":[{"time":0,"x":0,"y":0,"curve":"stepped"},{"time":0.3333,"x":0,"y":0,"curve":"stepped"},{"time":0.6666,"x":0,"y":0}],"scale":[{"time":0,"x":1,"y":1,"curve":"stepped"},{"time":0.3333,"x":1,"y":1,"curve":"stepped"},{"time":0.6666,"x":1,"y":1}]},"bone8":{"rotate":[{"time":0,"angle":-24.45,"curve":[0.256,0,0.619,0.46]},{"time":0.1666,"angle":-21.2,"curve":[0.365,0.45,0.754,1]},{"time":0.4,"angle":77.04,"curve":"stepped"},{"time":0.6666,"angle":77.04}],"translate":[{"time":0,"x":0,"y":0,"curve":[0.25,0,0.75,1]},{"time":0.4,"x":-6.32,"y":-7.26,"curve":"stepped"},{"time":0.6666,"x":-6.32,"y":-7.26}],"scale":[{"time":0,"x":1,"y":1,"curve":"stepped"},{"time":0.4,"x":1,"y":1,"curve":"stepped"},{"time":0.6666,"x":1,"y":1}]},"bone12":{"rotate":[{"time":0,"angle":0,"curve":"stepped"},{"time":0.3333,"angle":0,"curve":"stepped"},{"time":0.6666,"angle":0}],"translate":[{"time":0,"x":0,"y":0,"curve":"stepped"},{"time":0.3333,"x":0,"y":0,"curve":"stepped"},{"time":0.6666,"x":0,"y":0}],"scale":[{"time":0,"x":1,"y":1,"curve":"stepped"},{"time":0.3333,"x":1,"y":1,"curve":"stepped"},{"time":0.6666,"x":1,"y":1}]},"bone11":{"rotate":[{"time":0,"angle":0,"curve":[0.25,0,0.75,1]},{"time":0.3333,"angle":-82.82,"curve":"stepped"},{"time":0.6666,"angle":-82.82}],"translate":[{"time":0,"x":0,"y":0,"curve":[0.25,0,0.75,1]},{"time":0.3333,"x":8.37,"y":9.9,"curve":"stepped"},{"time":0.6666,"x":8.37,"y":9.9}],"scale":[{"time":0,"x":1,"y":1,"curve":"stepped"},{"time":0.3333,"x":1,"y":1,"curve":"stepped"},{"time":0.6666,"x":1,"y":1}]},"bone7":{"rotate":[{"time":0,"angle":5.89,"curve":"stepped"},{"time":0.3333,"angle":5.89,"curve":"stepped"},{"time":0.6666,"angle":5.89}],"translate":[{"time":0,"x":-2.28,"y":0.44,"curve":"stepped"},{"time":0.3333,"x":-2.28,"y":0.44,"curve":"stepped"},{"time":0.6666,"x":-2.28,"y":0.44}],"scale":[{"time":0,"x":1,"y":1,"curve":"stepped"},{"time":0.3333,"x":1,"y":1,"curve":"stepped"},{"time":0.6666,"x":1,"y":1}]},"bone6":{"rotate":[{"time":0,"angle":298.58,"curve":[0.25,0,0.75,1]},{"time":0.3333,"angle":-84.14,"curve":"stepped"},{"time":0.6666,"angle":-84.14}],"translate":[{"time":0,"x":-1.24,"y":6.18,"curve":"stepped"},{"time":0.3333,"x":-1.24,"y":6.18,"curve":"stepped"},{"time":0.6666,"x":-1.24,"y":6.18}],"scale":[{"time":0,"x":1,"y":1,"curve":"stepped"},{"time":0.3333,"x":1,"y":1,"curve":"stepped"},{"time":0.6666,"x":1,"y":1}]},"bone13":{"rotate":[{"time":0,"angle":0,"curve":"stepped"},{"time":0.3333,"angle":0,"curve":"stepped"},{"time":0.6666,"angle":0}],"translate":[{"time":0,"x":0,"y":0,"curve":"stepped"},{"time":0.3333,"x":0,"y":0,"curve":"stepped"},{"time":0.6666,"x":0,"y":0}],"scale":[{"time":0,"x":1,"y":1,"curve":"stepped"},{"time":0.3333,"x":1,"y":1,"curve":"stepped"},{"time":0.6666,"x":1,"y":1}]},"bone10":{"rotate":[{"time":0,"angle":27.33,"curve":[0.25,0,0.75,1]},{"time":0.1666,"angle":9.27,"curve":[0.25,0,0.75,1]},{"time":0.3333,"angle":42.82,"curve":[0.25,0,0.75,1]},{"time":0.6666,"angle":9.61}],"translate":[{"time":0,"x":0,"y":0,"curve":[0.25,0,0.75,1]},{"time":0.1666,"x":23.89,"y":25.47,"curve":[0.25,0,0.75,1]},{"time":0.3333,"x":19.06,"y":57.63,"curve":[0.25,0,0.75,1]},{"time":0.6666,"x":44.72,"y":62.24}],"scale":[{"time":0,"x":1,"y":1,"curve":"stepped"},{"time":0.1666,"x":1,"y":1,"curve":"stepped"},{"time":0.6666,"x":1,"y":1}]},"bone5":{"rotate":[{"time":0,"angle":-26.1,"curve":[0.25,0,0.75,1]},{"time":0.3333,"angle":14,"curve":"stepped"},{"time":0.6666,"angle":14}],"translate":[{"time":0,"x":-2.94,"y":2.23,"curve":"stepped"},{"time":0.3333,"x":-2.94,"y":2.23,"curve":"stepped"},{"time":0.6666,"x":-2.94,"y":2.23}],"scale":[{"time":0,"x":1,"y":1,"curve":"stepped"},{"time":0.3333,"x":1,"y":1,"curve":"stepped"},{"time":0.6666,"x":1,"y":1}]},"bone4":{"rotate":[{"time":0,"angle":0,"curve":"stepped"},{"time":0.3333,"angle":0,"curve":"stepped"},{"time":0.6666,"angle":0}],"translate":[{"time":0,"x":0,"y":0,"curve":[0.25,0,0.75,1]},{"time":0.3333,"x":-2.12,"y":-4.47,"curve":"stepped"},{"time":0.6666,"x":-2.12,"y":-4.47}],"scale":[{"time":0,"x":1,"y":1,"curve":[0.25,0,0.75,1]},{"time":0.3333,"x":1,"y":0.764,"curve":"stepped"},{"time":0.6666,"x":1,"y":0.764}]},"bone3":{"rotate":[{"time":0,"angle":46.12,"curve":[0.25,0,0.75,1]},{"time":0.3333,"angle":177.74,"curve":"stepped"},{"time":0.6666,"angle":177.74}],"translate":[{"time":0,"x":-1.74,"y":1.33,"curve":[0.25,0,0.75,1]},{"time":0.3333,"x":-9.49,"y":-8.06,"curve":"stepped"},{"time":0.6666,"x":-9.49,"y":-8.06}],"scale":[{"time":0,"x":1,"y":1,"curve":"stepped"},{"time":0.3333,"x":1,"y":1,"curve":"stepped"},{"time":0.6666,"x":1,"y":1}]},"bone2":{"rotate":[{"time":0,"angle":0,"curve":[0.25,0,0.75,1]},{"time":0.3333,"angle":-72.87,"curve":"stepped"},{"time":0.6666,"angle":-72.87}],"translate":[{"time":0,"x":0,"y":0,"curve":"stepped"},{"time":0.3333,"x":0,"y":0,"curve":"stepped"},{"time":0.6666,"x":0,"y":0}],"scale":[{"time":0,"x":1,"y":1,"curve":"stepped"},{"time":0.3333,"x":1,"y":1,"curve":"stepped"},{"time":0.6666,"x":1,"y":1}]},"bone":{"rotate":[{"time":0,"angle":-12,"curve":"stepped"},{"time":0.3333,"angle":-12,"curve":"stepped"},{"time":0.6666,"angle":-12}],"translate":[{"time":0,"x":0,"y":0,"curve":"stepped"},{"time":0.3333,"x":0,"y":0,"curve":"stepped"},{"time":0.6666,"x":0,"y":0}],"scale":[{"time":0,"x":1,"y":1,"curve":"stepped"},{"time":0.3333,"x":1,"y":1,"curve":"stepped"},{"time":0.6666,"x":1,"y":1}]}},"ffd":{"default":{"bone8":{"common_squirrel_earth_head_01":[{"time":0,"curve":"stepped"},{"time":0.6666}]},"common_squirrel_earth_acc_2":{"common_squirrel_earth_acc_02":[{"time":0,"curve":"stepped"},{"time":0.6666}]},"common_squirrel_earth_body_2":{"common_squirrel_earth_body_01":[{"time":0,"offset":4,"vertices":[-1.16438,-2.19264,0.31402,2.14815],"curve":[0.25,0,0.75,1]},{"time":0.3333,"offset":2,"vertices":[-3.82335,-5.33357,-4.98773,-7.52622,0.31402,2.14815,-4.87292,-4.55286,-7.47132,-7.94135,-7.47132,-7.94135,-4.87292,-4.55286,-4.87292,-4.55286,-2.56469,-2.39624,-5.54002,-4.69581,-5.38026,-4.86678,-2.56469,-2.39624],"curve":"stepped"},{"time":0.6666,"offset":2,"vertices":[-3.82335,-5.33357,-4.98773,-7.52622,0.31402,2.14815,-4.87292,-4.55286,-7.47132,-7.94135,-7.47132,-7.94135,-4.87292,-4.55286,-4.87292,-4.55286,-2.56469,-2.39624,-5.54002,-4.69581,-5.38026,-4.86678,-2.56469,-2.39624]}]},"common_squirrel_earth_tail_2":{"common_squirrel_earth_tail_01":[{"time":0,"curve":"stepped"},{"time":0.6666}]}}},"drawOrder":[{"time":0,"offsets":[{"slot":"common_squirrel_earth_acc_2","offset":-5}]},{"time":0.6666,"offsets":[{"slot":"common_squirrel_earth_acc_2","offset":-5}]}]},"die_idle":{"slots":{"bone4":{"attachment":[{"time":0,"name":"common_squirrel_earth_leg_01"}]},"bone7":{"attachment":[{"time":0,"name":null}]},"bone8":{"attachment":[{"time":0,"name":"common_squirrel_earth_head_01"}]},"bone10":{"attachment":[{"time":0,"name":"common_squirrel_earth_weapon_01"}]},"common_squirrel_earth_acc_01":{"attachment":[{"time":0,"name":"common_squirrel_earth_acc_01"}]},"common_squirrel_earth_acc_2":{"attachment":[{"time":0,"name":"common_squirrel_earth_acc_02"}],"color":[{"time":0,"color":"ffffffff"}]},"common_squirrel_earth_arm_1":{"attachment":[{"time":0,"name":null}]},"common_squirrel_earth_arm_01":{"attachment":[{"time":0,"name":null}]},"common_squirrel_earth_arm_2":{"attachment":[{"time":0,"name":null}]},"common_squirrel_earth_arm_3":{"attachment":[{"time":0,"name":"common_squirrel_earth_arm_01"}],"color":[{"time":0,"color":"ffffff00"}]},"common_squirrel_earth_arm_4":{"attachment":[{"time":0,"name":"common_squirrel_earth_arm_02"}]},"common_squirrel_earth_arm_5":{"attachment":[{"time":0,"name":"common_squirrel_earth_arm_02"}],"color":[{"time":0,"color":"ffffffff"}]},"common_squirrel_earth_body_1":{"attachment":[{"time":0,"name":null}]},"common_squirrel_earth_body_01":{"attachment":[{"time":0,"name":null}]},"common_squirrel_earth_body_2":{"attachment":[{"time":0,"name":"common_squirrel_earth_body_01"}]},"common_squirrel_earth_head_1":{"attachment":[{"time":0,"name":null}]},"common_squirrel_earth_head_2":{"attachment":[{"time":0,"name":"common_squirrel_earth_head_02"}]},"common_squirrel_earth_leg_1":{"attachment":[{"time":0,"name":null}]},"common_squirrel_earth_leg_01":{"attachment":[{"time":0,"name":null}]},"common_squirrel_earth_leg_2":{"attachment":[{"time":0,"name":null}]},"common_squirrel_earth_leg_3":{"attachment":[{"time":0,"name":null}]},"common_squirrel_earth_leg_4":{"attachment":[{"time":0,"name":"common_squirrel_earth_leg_02"}]},"common_squirrel_earth_tail_1":{"attachment":[{"time":0,"name":null}]},"common_squirrel_earth_tail_2":{"attachment":[{"time":0,"name":"common_squirrel_earth_tail_01"}]}},"bones":{"bone7":{"rotate":[{"time":0,"angle":5.89}],"translate":[{"time":0,"x":-2.28,"y":0.44}],"scale":[{"time":0,"x":1,"y":1}]},"bone6":{"rotate":[{"time":0,"angle":-84.14}],"translate":[{"time":0,"x":-1.24,"y":6.18}],"scale":[{"time":0,"x":1,"y":1}]},"bone2":{"rotate":[{"time":0,"angle":-72.87}],"translate":[{"time":0,"x":0,"y":0}],"scale":[{"time":0,"x":1,"y":1}]},"bone10":{"rotate":[{"time":0,"angle":9.61}],"translate":[{"time":0,"x":44.72,"y":62.24}],"scale":[{"time":0,"x":1,"y":1}]},"bone":{"rotate":[{"time":0,"angle":-12}],"translate":[{"time":0,"x":0,"y":0}],"scale":[{"time":0,"x":1,"y":1}]},"bone5":{"rotate":[{"time":0,"angle":14}],"translate":[{"time":0,"x":-2.94,"y":2.23}],"scale":[{"time":0,"x":1,"y":1}]},"bone13":{"rotate":[{"time":0,"angle":0}],"translate":[{"time":0,"x":0,"y":0}],"scale":[{"time":0,"x":1,"y":1}]},"bone8":{"rotate":[{"time":0,"angle":77.04}],"translate":[{"time":0,"x":-6.32,"y":-7.26}],"scale":[{"time":0,"x":1,"y":1}]},"bone4":{"rotate":[{"time":0,"angle":0}],"translate":[{"time":0,"x":-2.12,"y":-4.47}],"scale":[{"time":0,"x":1,"y":0.764}]},"bone3":{"rotate":[{"time":0,"angle":177.74}],"translate":[{"time":0,"x":-9.49,"y":-8.06}],"scale":[{"time":0,"x":1,"y":1}]},"bone11":{"rotate":[{"time":0,"angle":-82.82}],"translate":[{"time":0,"x":8.37,"y":9.9}],"scale":[{"time":0,"x":1,"y":1}]},"bone9":{"rotate":[{"time":0,"angle":0}],"translate":[{"time":0,"x":0,"y":0}],"scale":[{"time":0,"x":1,"y":1}]},"root":{"rotate":[{"time":0,"angle":0}],"translate":[{"time":0,"x":0,"y":0}],"scale":[{"time":0,"x":1,"y":1}]},"bone12":{"rotate":[{"time":0,"angle":0}],"translate":[{"time":0,"x":0,"y":0}],"scale":[{"time":0,"x":1,"y":1}]}},"ffd":{"default":{"bone8":{"common_squirrel_earth_head_01":[{"time":0}]},"common_squirrel_earth_acc_2":{"common_squirrel_earth_acc_02":[{"time":0}]},"common_squirrel_earth_body_2":{"common_squirrel_earth_body_01":[{"time":0,"offset":2,"vertices":[-3.82335,-5.33357,-4.98773,-7.52622,0.31402,2.14815,-4.87292,-4.55286,-7.47132,-7.94135,-7.47132,-7.94135,-4.87292,-4.55286,-4.87292,-4.55286,-2.56469,-2.39624,-5.54002,-4.69581,-5.38026,-4.86678,-2.56469,-2.39624]}]},"common_squirrel_earth_tail_2":{"common_squirrel_earth_tail_01":[{"time":0}]}}},"drawOrder":[{"time":0,"offsets":[{"slot":"common_squirrel_earth_acc_2","offset":-5}]}]},"idle":{"slots":{"common_squirrel_earth_acc_2":{"attachment":[{"time":0,"name":"common_squirrel_earth_acc_02"},{"time":1,"name":"common_squirrel_earth_acc_02"}],"color":[{"time":0,"color":"ffffffff","curve":"stepped"},{"time":1,"color":"ffffffff"}]}},"bones":{"bone":{"rotate":[{"time":0,"angle":-12},{"time":0.5,"angle":0},{"time":1,"angle":-12}],"translate":[{"time":0,"x":0,"y":0},{"time":0.5,"x":0,"y":11.78},{"time":0.5666,"x":0.06,"y":12.71},{"time":1,"x":0,"y":0}],"scale":[{"time":0,"x":1,"y":1,"curve":"stepped"},{"time":0.5,"x":1,"y":1,"curve":"stepped"},{"time":1,"x":1,"y":1}]},"bone9":{"rotate":[{"time":0,"angle":0},{"time":0.1666,"angle":-7.13},{"time":0.3333,"angle":5.88},{"time":0.5,"angle":25.36},{"time":0.6,"angle":45.55},{"time":1,"angle":0}],"translate":[{"time":0,"x":0,"y":0,"curve":"stepped"},{"time":0.5,"x":0,"y":0,"curve":"stepped"},{"time":1,"x":0,"y":0}],"scale":[{"time":0,"x":1,"y":1,"curve":"stepped"},{"time":0.5,"x":1,"y":1,"curve":"stepped"},{"time":1,"x":1,"y":1}]},"bone8":{"rotate":[{"time":0,"angle":-24.45},{"time":0.1666,"angle":-31.96},{"time":0.5,"angle":6.38},{"time":1,"angle":-24.45}],"translate":[{"time":0,"x":0,"y":0,"curve":"stepped"},{"time":0.5,"x":0,"y":0,"curve":"stepped"},{"time":1,"x":0,"y":0}],"scale":[{"time":0,"x":1,"y":1,"curve":"stepped"},{"time":0.5,"x":1,"y":1,"curve":"stepped"},{"time":1,"x":1,"y":1}]},"bone11":{"rotate":[{"time":0,"angle":0,"curve":"stepped"},{"time":0.5,"angle":0,"curve":"stepped"},{"time":1,"angle":0}],"translate":[{"time":0,"x":0,"y":0,"curve":"stepped"},{"time":0.5,"x":0,"y":0,"curve":"stepped"},{"time":1,"x":0,"y":0}],"scale":[{"time":0,"x":1,"y":1,"curve":"stepped"},{"time":0.5,"x":1,"y":1,"curve":"stepped"},{"time":1,"x":1,"y":1}]},"bone7":{"rotate":[{"time":0,"angle":5.89},{"time":0.3333,"angle":5.75},{"time":0.5,"angle":0},{"time":1,"angle":5.89}],"translate":[{"time":0,"x":-2.28,"y":0.44},{"time":0.5,"x":0,"y":0},{"time":1,"x":-2.28,"y":0.44}],"scale":[{"time":0,"x":1,"y":1},{"time":0.5,"x":1,"y":1.025},{"time":1,"x":1,"y":1}]},"bone6":{"rotate":[{"time":0,"angle":298.58},{"time":0.5,"angle":0},{"time":1,"angle":298.58}],"translate":[{"time":0,"x":-1.24,"y":6.18},{"time":0.5,"x":0,"y":0},{"time":0.8333,"x":-1.48,"y":4.15},{"time":1,"x":-1.24,"y":6.18}],"scale":[{"time":0,"x":1,"y":1,"curve":"stepped"},{"time":0.5,"x":1,"y":1,"curve":"stepped"},{"time":1,"x":1,"y":1}]},"bone10":{"rotate":[{"time":0,"angle":27.33},{"time":0.5,"angle":0},{"time":1,"angle":27.33}],"translate":[{"time":0,"x":0,"y":0,"curve":"stepped"},{"time":0.5,"x":0,"y":0,"curve":"stepped"},{"time":1,"x":0,"y":0}],"scale":[{"time":0,"x":1,"y":1,"curve":"stepped"},{"time":0.5,"x":1,"y":1,"curve":"stepped"},{"time":1,"x":1,"y":1}]},"bone5":{"rotate":[{"time":0,"angle":-26.1},{"time":0.1666,"angle":1.94},{"time":0.3333,"angle":-16.45},{"time":0.5,"angle":0},{"time":0.8333,"angle":-16.45},{"time":1,"angle":-26.1}],"translate":[{"time":0,"x":-2.94,"y":2.23},{"time":0.5,"x":0,"y":0},{"time":1,"x":-2.94,"y":2.23}],"scale":[{"time":0,"x":1,"y":1,"curve":"stepped"},{"time":0.5,"x":1,"y":1,"curve":"stepped"},{"time":1,"x":1,"y":1}]},"bone4":{"rotate":[{"time":0,"angle":0},{"time":0.5,"angle":-28.02},{"time":1,"angle":0}],"translate":[{"time":0,"x":0,"y":0},{"time":0.5,"x":0.22,"y":1.58},{"time":1,"x":0,"y":0}],"scale":[{"time":0,"x":1,"y":1,"curve":"stepped"},{"time":0.5,"x":1,"y":1,"curve":"stepped"},{"time":1,"x":1,"y":1}]},"bone3":{"rotate":[{"time":0,"angle":46.12},{"time":0.1666,"angle":-19.71},{"time":0.3333,"angle":53.38},{"time":0.5,"angle":0},{"time":0.6666,"angle":71.7},{"time":1,"angle":46.12}],"translate":[{"time":0,"x":-1.74,"y":1.33},{"time":0.5,"x":0,"y":0},{"time":1,"x":-1.74,"y":1.33}],"scale":[{"time":0,"x":1,"y":1,"curve":"stepped"},{"time":0.5,"x":1,"y":1,"curve":"stepped"},{"time":1,"x":1,"y":1}]},"bone2":{"rotate":[{"time":0,"angle":0},{"time":0.5,"angle":2.56},{"time":1,"angle":0}],"translate":[{"time":0,"x":0,"y":0,"curve":"stepped"},{"time":0.5,"x":0,"y":0,"curve":"stepped"},{"time":1,"x":0,"y":0}],"scale":[{"time":0,"x":1,"y":1},{"time":0.5,"x":1.016,"y":1},{"time":1,"x":1,"y":1}]},"bone12":{"translate":[{"time":0,"x":0,"y":0},{"time":0.5,"x":0.97,"y":0.59},{"time":0.6666,"x":0,"y":0},{"time":1,"x":0,"y":0}]}},"ffd":{"default":{"bone8":{"common_squirrel_earth_head_01":[{"time":0},{"time":0.5,"vertices":[-0.77456,-2.38382,0,0,-0.53345,-2.10213,-1.93898,-3.63051,-6.51472,-2.94734,-7.96143,0.70921,-8.36663,-0.2193,-13.83636,2.95898,-14.07092,-1.30962,-8.42302,-2.44661,-4.18587,-0.45391,-3.16499,-2.44648,0,0,0,0,0,0,0.73864,2.91063,0,0,0,0,0,0,0,0,0,0,0,0,0,0,0,0,-0.64117,-0.52161,-1.33364,-2.58204,-1.2722,0.3338,0,0,-0.0308,1.21537,-1.5441,1.26748,-1.13357,-2.46207,-1.14384,-3.83916,-0.85657,-2.70725,-2.90332,-4.75724,-2.26214,-4.23563,-2.30827,-5.08585,0,0,-14.17356,0.95942,-13.09705,-3.44258,-9.16163,-5.35727,-7.0841,-4.52263,-0.26677,1.65386,0.17949,2.74405,-0.3027,2.18862,-0.14368,2.10733,0.21029,1.49705,-1.23627,-0.19302,-0.4924,-1.94044,-1.0054,-1.28841,-0.24621,-0.97022,0,0,0.15903,-0.04172,-0.5847,-3.64092,-0.06659,-3.60439]},{"time":1}]},"common_squirrel_earth_acc_2":{"common_squirrel_earth_acc_02":[{"time":0},{"time":0.5,"vertices":[1.49459,5.22211,-16.02912,8.06432,-10.00227,6.15143,0.12263,3.34227,-2.65975,2.16723,-0.13204,1.21798,2.28732,-2.08574,-5.98463,4.87627,-1.54219,1.92278]},{"time":1}]},"common_squirrel_earth_body_2":{"common_squirrel_earth_body_01":[{"time":0,"offset":4,"vertices":[-1.16438,-2.19264,0.31402,2.14815]},{"time":0.5,"offset":4,"vertices":[-0.58219,-1.09632,0.15701,1.07407]},{"time":1,"offset":4,"vertices":[-1.16438,-2.19264,0.31402,2.14815]}]}}},"drawOrder":[{"time":0,"offsets":[{"slot":"common_squirrel_earth_acc_2","offset":-5}]},{"time":1,"offsets":[{"slot":"common_squirrel_earth_acc_2","offset":-5}]}]},"skill_1":{"slots":{"bone4":{"attachment":[{"time":0,"name":"common_squirrel_earth_leg_01"},{"time":0.3333,"name":"common_squirrel_earth_leg_01"},{"time":1.3333,"name":"common_squirrel_earth_leg_01"},{"time":1.6666,"name":"common_squirrel_earth_leg_01"}]},"bone7":{"attachment":[{"time":0,"name":null},{"time":0.3333,"name":null},{"time":1.3333,"name":null},{"time":1.6666,"name":null}]},"bone8":{"attachment":[{"time":0,"name":"common_squirrel_earth_head_01"},{"time":0.3333,"name":"common_squirrel_earth_head_01"},{"time":1.3333,"name":"common_squirrel_earth_head_01"},{"time":1.6666,"name":"common_squirrel_earth_head_01"}]},"bone10":{"attachment":[{"time":0,"name":"common_squirrel_earth_weapon_01"},{"time":0.3333,"name":"common_squirrel_earth_weapon_01"},{"time":1.3333,"name":"common_squirrel_earth_weapon_01"},{"time":1.6666,"name":"common_squirrel_earth_weapon_01"}],"color":[{"time":0,"color":"ffffffff","curve":[0.25,0,0.75,1]},{"time":0.1666,"color":"ffffff00","curve":"stepped"},{"time":0.3333,"color":"ffffff00","curve":"stepped"},{"time":1.3333,"color":"ffffff00","curve":"stepped"},{"time":1.5666,"color":"ffffff00","curve":[0.25,0,0.75,1]},{"time":1.6666,"color":"ffffffff"}]},"common_squirrel_earth_acc_01":{"attachment":[{"time":0,"name":"common_squirrel_earth_acc_01"},{"time":1.6666,"name":"common_squirrel_earth_acc_01"}]},"common_squirrel_earth_acc_2":{"attachment":[{"time":0,"name":"common_squirrel_earth_acc_02"},{"time":0.3333,"name":"common_squirrel_earth_acc_02"},{"time":1.3333,"name":"common_squirrel_earth_acc_02"},{"time":1.6666,"name":"common_squirrel_earth_acc_02"}],"color":[{"time":0,"color":"ffffffff","curve":[0.25,0,0.75,1]},{"time":0.1666,"color":"ffffff00","curve":"stepped"},{"time":0.3333,"color":"ffffff00","curve":"stepped"},{"time":1.3333,"color":"ffffff00","curve":"stepped"},{"time":1.5666,"color":"ffffff00","curve":[0.25,0,0.75,1]},{"time":1.6666,"color":"ffffffff"}]},"common_squirrel_earth_arm_1":{"attachment":[{"time":0,"name":null},{"time":0.3333,"name":null},{"time":1.3333,"name":null},{"time":1.6666,"name":null}]},"common_squirrel_earth_arm_01":{"attachment":[{"time":0,"name":null},{"time":0.3333,"name":null},{"time":1.3333,"name":null},{"time":1.6666,"name":null}]},"common_squirrel_earth_arm_2":{"attachment":[{"time":0,"name":null},{"time":0.3333,"name":null},{"time":1.3333,"name":null},{"time":1.6666,"name":null}]},"common_squirrel_earth_arm_3":{"attachment":[{"time":0,"name":"common_squirrel_earth_arm_01"},{"time":0.3333,"name":"common_squirrel_earth_arm_01"},{"time":1.3333,"name":"common_squirrel_earth_arm_01"},{"time":1.6666,"name":"common_squirrel_earth_arm_01"}],"color":[{"time":0,"color":"ffffffff","curve":"stepped"},{"time":0.1666,"color":"ffffffff","curve":[0.25,0,0.75,1]},{"time":0.3333,"color":"ffffff00","curve":"stepped"},{"time":1.3333,"color":"ffffff00","curve":"stepped"},{"time":1.5,"color":"ffffff00","curve":[0.25,0,0.75,1]},{"time":1.6666,"color":"ffffffff"}]},"common_squirrel_earth_arm_4":{"attachment":[{"time":0,"name":"common_squirrel_earth_arm_02"},{"time":0.3333,"name":"common_squirrel_earth_arm_02"},{"time":1.3333,"name":"common_squirrel_earth_arm_02"},{"time":1.6666,"name":"common_squirrel_earth_arm_02"}]},"common_squirrel_earth_arm_5":{"attachment":[{"time":0,"name":"common_squirrel_earth_arm_02"},{"time":0.3333,"name":"common_squirrel_earth_arm_02"},{"time":1.3333,"name":"common_squirrel_earth_arm_02"},{"time":1.6666,"name":"common_squirrel_earth_arm_02"}],"color":[{"time":0,"color":"ffffff00","curve":"stepped"},{"time":0.1666,"color":"ffffff00","curve":[0.25,0,0.75,1]},{"time":0.3333,"color":"ffffffff","curve":"stepped"},{"time":1.3333,"color":"ffffffff","curve":"stepped"},{"time":1.5,"color":"ffffffff","curve":[0.25,0,0.75,1]},{"time":1.6666,"color":"ffffff00"}]},"common_squirrel_earth_body_01":{"attachment":[{"time":0,"name":null},{"time":0.3333,"name":null},{"time":1.3333,"name":null},{"time":1.6666,"name":null}]},"common_squirrel_earth_body_1":{"attachment":[{"time":0,"name":null},{"time":0.3333,"name":null},{"time":1.3333,"name":null},{"time":1.6666,"name":null}]},"common_squirrel_earth_body_2":{"attachment":[{"time":0,"name":"common_squirrel_earth_body_01"},{"time":0.3333,"name":"common_squirrel_earth_body_01"},{"time":1.3333,"name":"common_squirrel_earth_body_01"},{"time":1.6666,"name":"common_squirrel_earth_body_01"}]},"common_squirrel_earth_head_1":{"attachment":[{"time":0,"name":null},{"time":0.3333,"name":null},{"time":1.3333,"name":null},{"time":1.6666,"name":null}]},"common_squirrel_earth_head_2":{"attachment":[{"time":0,"name":"common_squirrel_earth_head_02"},{"time":1.6666,"name":"common_squirrel_earth_head_02"}]},"common_squirrel_earth_leg_1":{"attachment":[{"time":0,"name":null},{"time":0.3333,"name":null},{"time":1.3333,"name":null},{"time":1.6666,"name":null}]},"common_squirrel_earth_leg_01":{"attachment":[{"time":0,"name":null},{"time":0.3333,"name":null},{"time":1.3333,"name":null},{"time":1.6666,"name":null}]},"common_squirrel_earth_leg_2":{"attachment":[{"time":0,"name":null},{"time":0.3333,"name":null},{"time":1.3333,"name":null},{"time":1.6666,"name":null}]},"common_squirrel_earth_leg_3":{"attachment":[{"time":0,"name":null},{"time":0.3333,"name":null},{"time":1.3333,"name":null},{"time":1.6666,"name":null}]},"common_squirrel_earth_leg_4":{"attachment":[{"time":0,"name":"common_squirrel_earth_leg_02"},{"time":0.3333,"name":"common_squirrel_earth_leg_02"},{"time":1.3333,"name":"common_squirrel_earth_leg_02"},{"time":1.6666,"name":"common_squirrel_earth_leg_02"}]},"common_squirrel_earth_tail_1":{"attachment":[{"time":0,"name":null},{"time":0.3333,"name":null},{"time":1.3333,"name":null},{"time":1.6666,"name":null}]},"common_squirrel_earth_tail_2":{"attachment":[{"time":0,"name":"common_squirrel_earth_tail_01"},{"time":0.3333,"name":"common_squirrel_earth_tail_01"},{"time":1.3333,"name":"common_squirrel_earth_tail_01"},{"time":1.6666,"name":"common_squirrel_earth_tail_01"}]}},"bones":{"bone4":{"rotate":[{"time":0,"angle":0,"curve":"stepped"},{"time":1.6666,"angle":0}],"translate":[{"time":0,"x":0,"y":0,"curve":"stepped"},{"time":1.6666,"x":0,"y":0}],"scale":[{"time":0,"x":1,"y":1,"curve":"stepped"},{"time":0.3333,"x":1,"y":1,"curve":[0.368,0.47,0.753,1]},{"time":0.5,"x":0.884,"y":1.026,"curve":[0.368,0.47,0.753,1]},{"time":0.6666,"x":1,"y":1,"curve":[0.368,0.47,0.753,1]},{"time":0.8333,"x":0.884,"y":1.026,"curve":[0.368,0.47,0.753,1]},{"time":1,"x":1,"y":1,"curve":[0.368,0.47,0.753,1]},{"time":1.1666,"x":0.884,"y":1.026,"curve":[0.332,0.33,0.667,0.66]},{"time":1.2,"x":0.914,"y":1.019,"curve":[0.379,0.52,0.746,1]},{"time":1.3333,"x":1,"y":1,"curve":"stepped"},{"time":1.6666,"x":1,"y":1}]},"bone6":{"rotate":[{"time":0,"angle":-61.41,"curve":"stepped"},{"time":1.6666,"angle":-61.41}],"translate":[{"time":0,"x":-1.24,"y":6.18,"curve":"stepped"},{"time":1.6666,"x":-1.24,"y":6.18}],"scale":[{"time":0,"x":1,"y":1,"curve":"stepped"},{"time":0.3333,"x":1,"y":1,"curve":[0.368,0.47,0.753,1]},{"time":0.5,"x":0.884,"y":1.026,"curve":[0.368,0.47,0.753,1]},{"time":0.6666,"x":1,"y":1,"curve":[0.368,0.47,0.753,1]},{"time":0.8333,"x":0.884,"y":1.026,"curve":[0.368,0.47,0.753,1]},{"time":1,"x":1,"y":1,"curve":[0.368,0.47,0.753,1]},{"time":1.1666,"x":0.884,"y":1.026,"curve":[0.332,0.33,0.667,0.66]},{"time":1.2,"x":0.914,"y":1.019,"curve":[0.379,0.52,0.746,1]},{"time":1.3333,"x":1,"y":1,"curve":"stepped"},{"time":1.6666,"x":1,"y":1}]},"bone9":{"rotate":[{"time":0,"angle":0,"curve":"stepped"},{"time":1.6666,"angle":0}],"translate":[{"time":0,"x":0,"y":0,"curve":"stepped"},{"time":1.6666,"x":0,"y":0}],"scale":[{"time":0,"x":1,"y":1,"curve":"stepped"},{"time":1.6666,"x":1,"y":1}]},"bone10":{"rotate":[{"time":0,"angle":27.33,"curve":[0.25,0,0.75,1]},{"time":0.1666,"angle":96.27,"curve":[0.25,0,0.75,1]},{"time":0.3333,"angle":87.3,"curve":"stepped"},{"time":0.5,"angle":87.3,"curve":"stepped"},{"time":1.3333,"angle":87.3,"curve":[0.25,0,0.75,1]},{"time":1.5,"angle":96.27,"curve":[0.25,0,0.75,1]},{"time":1.6666,"angle":27.33}],"translate":[{"time":0,"x":0,"y":0,"curve":"stepped"},{"time":1.6666,"x":0,"y":0}],"scale":[{"time":0,"x":1,"y":1,"curve":"stepped"},{"time":1.6666,"x":1,"y":1}]},"bone3":{"rotate":[{"time":0,"angle":46.12,"curve":[0.25,0,0.75,1]},{"time":0.3333,"angle":-230.05,"curve":"stepped"},{"time":1.3333,"angle":-230.05,"curve":[0.25,0,0.75,1]},{"time":1.6666,"angle":46.12}],"translate":[{"time":0,"x":-1.74,"y":1.33,"curve":[0.25,0,0.75,1]},{"time":0.3333,"x":-3.82,"y":0.41,"curve":"stepped"},{"time":1.3333,"x":-3.82,"y":0.41,"curve":[0.25,0,0.75,1]},{"time":1.6666,"x":-1.74,"y":1.33}],"scale":[{"time":0,"x":1,"y":1,"curve":[0.25,0,0.75,1]},{"time":0.3333,"x":1.289,"y":1,"curve":[0.283,0.11,0.629,0.5]},{"time":0.5,"x":1,"y":1,"curve":[0.283,0.11,0.629,0.5]},{"time":0.6666,"x":1.289,"y":1,"curve":[0.283,0.11,0.629,0.5]},{"time":0.8333,"x":1,"y":1,"curve":[0.283,0.11,0.629,0.5]},{"time":1,"x":1.289,"y":1,"curve":[0.283,0.11,0.629,0.5]},{"time":1.1666,"x":1,"y":1,"curve":[0.319,0.22,0.653,0.56]},{"time":1.2,"x":1.034,"y":1,"curve":[0.298,0.19,0.64,0.56]},{"time":1.3333,"x":1.289,"y":1,"curve":[0.25,0,0.75,1]},{"time":1.6666,"x":1,"y":1}]},"bone13":{"rotate":[{"time":0,"angle":0,"curve":"stepped"},{"time":1.6666,"angle":0}],"translate":[{"time":0,"x":0,"y":0,"curve":"stepped"},{"time":1.6666,"x":0,"y":0}],"scale":[{"time":0,"x":1,"y":1,"curve":"stepped"},{"time":1.6666,"x":1,"y":1}]},"bone":{"rotate":[{"time":0,"angle":-12,"curve":"stepped"},{"time":1.6666,"angle":-12}],"translate":[{"time":0,"x":0,"y":0,"curve":"stepped"},{"time":1.6666,"x":0,"y":0}],"scale":[{"time":0,"x":1,"y":1,"curve":"stepped"},{"time":1.6666,"x":1,"y":1}]},"bone8":{"rotate":[{"time":0,"angle":-24.45,"curve":"stepped"},{"time":1.6666,"angle":-24.45}],"translate":[{"time":0,"x":0,"y":0,"curve":"stepped"},{"time":1.6666,"x":0,"y":0}],"scale":[{"time":0,"x":1,"y":1,"curve":"stepped"},{"time":1.6666,"x":1,"y":1}]},"root":{"rotate":[{"time":0,"angle":0,"curve":"stepped"},{"time":1.6666,"angle":0}],"translate":[{"time":0,"x":0,"y":0,"curve":"stepped"},{"time":1.6666,"x":0,"y":0}],"scale":[{"time":0,"x":1,"y":1,"curve":"stepped"},{"time":1.6666,"x":1,"y":1}]},"bone11":{"rotate":[{"time":0,"angle":0,"curve":[0.25,0,0.75,1]},{"time":0.3333,"angle":-30.7,"curve":[0.25,0,0.75,1]},{"time":0.5,"angle":0,"curve":[0.25,0,0.75,1]},{"time":0.6666,"angle":-30.7,"curve":[0.25,0,0.75,1]},{"time":0.8333,"angle":0,"curve":[0.25,0,0.75,1]},{"time":1,"angle":-30.7,"curve":[0.25,0,0.75,1]},{"time":1.1666,"angle":0,"curve":[0.25,0,0.75,1]},{"time":1.3333,"angle":-30.7,"curve":[0.25,0,0.75,1]},{"time":1.6666,"angle":0}],"translate":[{"time":0,"x":0,"y":0,"curve":[0.25,0,0.75,1]},{"time":0.3333,"x":-1.22,"y":2.94,"curve":[0.25,0,0.75,1]},{"time":0.5,"x":0,"y":0,"curve":[0.25,0,0.75,1]},{"time":0.6666,"x":-1.22,"y":2.94,"curve":[0.25,0,0.75,1]},{"time":0.8333,"x":0,"y":0,"curve":[0.25,0,0.75,1]},{"time":1,"x":-1.22,"y":2.94,"curve":[0.25,0,0.75,1]},{"time":1.1666,"x":0,"y":0,"curve":[0.25,0,0.75,1]},{"time":1.3333,"x":-1.22,"y":2.94,"curve":[0.25,0,0.75,1]},{"time":1.6666,"x":0,"y":0}],"scale":[{"time":0,"x":1,"y":1,"curve":"stepped"},{"time":1.6666,"x":1,"y":1}]},"bone12":{"rotate":[{"time":0,"angle":0,"curve":"stepped"},{"time":1.6666,"angle":0}],"translate":[{"time":0,"x":0,"y":0,"curve":[0.25,0,0.75,1]},{"time":0.3333,"x":0.97,"y":0.59,"curve":"stepped"},{"time":1.3333,"x":0.97,"y":0.59,"curve":[0.25,0,0.75,1]},{"time":1.6666,"x":0,"y":0}],"scale":[{"time":0,"x":1,"y":1,"curve":"stepped"},{"time":0.3333,"x":1,"y":1,"curve":"stepped"},{"time":0.5,"x":1,"y":1,"curve":"stepped"},{"time":1.2,"x":1,"y":1,"curve":"stepped"},{"time":1.3333,"x":1,"y":1,"curve":"stepped"},{"time":1.6666,"x":1,"y":1}]},"bone7":{"rotate":[{"time":0,"angle":5.89,"curve":"stepped"},{"time":1.6666,"angle":5.89}],"translate":[{"time":0,"x":-2.28,"y":0.44,"curve":"stepped"},{"time":1.6666,"x":-2.28,"y":0.44}],"scale":[{"time":0,"x":1,"y":1,"curve":"stepped"},{"time":1.6666,"x":1,"y":1}]},"bone2":{"rotate":[{"time":0,"angle":0,"curve":"stepped"},{"time":1.6666,"angle":0}],"translate":[{"time":0,"x":0,"y":0,"curve":"stepped"},{"time":1.6666,"x":0,"y":0}],"scale":[{"time":0,"x":1,"y":1,"curve":[0.25,0,0.75,1]},{"time":0.1666,"x":1.156,"y":1,"curve":[0.25,0,0.75,1]},{"time":0.3333,"x":1,"y":1,"curve":[0.25,0,0.75,1]},{"time":0.5,"x":1.13,"y":0.974,"curve":[0.25,0,0.75,1]},{"time":0.6666,"x":1,"y":1,"curve":[0.25,0,0.75,1]},{"time":0.8333,"x":1.13,"y":0.974,"curve":[0.25,0,0.75,1]},{"time":1,"x":1,"y":1,"curve":[0.25,0,0.75,1]},{"time":1.1666,"x":1.13,"y":0.974,"curve":[0.284,0,0.625,0.38]},{"time":1.2,"x":1.113,"y":0.977,"curve":[0.32,0.28,0.757,1]},{"time":1.3333,"x":1,"y":1,"curve":[0.25,0,0.75,1]},{"time":1.5,"x":1.156,"y":1,"curve":[0.25,0,0.75,1]},{"time":1.6666,"x":1,"y":1}]},"bone5":{"rotate":[{"time":0,"angle":-26.1,"curve":[0.25,0,0.75,1]},{"time":0.1666,"angle":42.83,"curve":[0.25,0,0.75,1]},{"time":0.3333,"angle":249.53,"curve":"stepped"},{"time":1.3333,"angle":249.53,"curve":[0.25,0,0.75,1]},{"time":1.5,"angle":42.83,"curve":[0.25,0,0.75,1]},{"time":1.6666,"angle":-26.1}],"translate":[{"time":0,"x":-2.94,"y":2.23,"curve":[0.25,0,0.75,1]},{"time":0.1666,"x":-2.64,"y":4.25,"curve":[0.25,0,0.75,1]},{"time":0.3333,"x":-3,"y":-2.32,"curve":"stepped"},{"time":1.3333,"x":-3,"y":-2.32,"curve":[0.25,0,0.75,1]},{"time":1.5,"x":-2.64,"y":4.25,"curve":[0.25,0,0.75,1]},{"time":1.6666,"x":-2.94,"y":2.23}],"scale":[{"time":0,"x":1,"y":1,"curve":[0.25,0,0.75,1]},{"time":0.3333,"x":1.268,"y":1,"curve":[0.361,0.64,0.697,1]},{"time":0.3666,"x":1.294,"y":1,"curve":[0.368,0.47,0.753,1]},{"time":0.5333,"x":1,"y":1,"curve":[0.368,0.47,0.753,1]},{"time":0.7,"x":1.294,"y":1,"curve":[0.368,0.47,0.753,1]},{"time":0.8666,"x":1,"y":1,"curve":[0.368,0.47,0.753,1]},{"time":1.0333,"x":1.294,"y":1,"curve":[0.368,0.47,0.753,1]},{"time":1.2,"x":1,"y":1,"curve":[0.352,0.39,0.717,0.84]},{"time":1.3333,"x":1.268,"y":1,"curve":[0.25,0,0.75,1]},{"time":1.6666,"x":1,"y":1}]}},"ffd":{"default":{"bone8":{"common_squirrel_earth_head_01":[{"time":0,"curve":[0.25,0,0.75,1]},{"time":0.3333,"vertices":[-0.77456,-2.38382,0,0,-0.53345,-2.10213,-1.93898,-3.63051,-6.51472,-2.94734,-7.96143,0.70921,-8.36663,-0.2193,-13.83636,2.95898,-14.07092,-1.30962,-8.42302,-2.44661,-4.18587,-0.45391,-3.16499,-2.44648,0,0,0,0,0,0,0.73864,2.91063,0,0,0,0,0,0,0,0,0,0,0,0,0,0,0,0,-0.64117,-0.52161,-1.33364,-2.58204,-1.2722,0.3338,0,0,-0.0308,1.21537,-1.5441,1.26748,-1.13357,-2.46207,-1.14384,-3.83916,-0.85657,-2.70725,-2.90332,-4.75724,-2.26214,-4.23563,-2.30827,-5.08585,0,0,-14.17356,0.95942,-13.09705,-3.44258,-9.16163,-5.35727,-7.0841,-4.52263,-0.26677,1.65386,0.17949,2.74405,-0.3027,2.18862,-0.14368,2.10733,0.21029,1.49705,-1.23627,-0.19302,-0.4924,-1.94044,-1.0054,-1.28841,-0.24621,-0.97022,0,0,0.15903,-0.04172,-0.5847,-3.64092,-0.06659,-3.60439],"curve":[0.25,0,0.75,1]},{"time":0.5,"vertices":[-0.77456,-2.38382,0,0,-0.53345,-2.10213,-1.93898,-3.63051,-8.5915,-2.13757,-4.66272,-2.97825,-1.91698,-5.31574,-3.73897,3.5073,-6.44981,2.67291,-5.78429,-2.89644,-3.66883,-0.75683,-3.16499,-2.44648,0,0,0,0,0,0,0.73864,2.91063,0,0,0,0,0,0,0,0,0,0,0,0,0,0,0,0,-0.64117,-0.52161,-1.33364,-2.58204,-1.2722,0.3338,0,0,-0.0308,1.21537,-1.5441,1.26748,-1.13357,-2.46207,-1.14384,-3.83916,-0.85657,-2.70725,-1.51807,-4.34898,-2.26214,-4.23563,-2.30827,-5.08585,0,0,-8.44081,1.31294,-10.49211,-1.75813,-7.58708,-3.41807,-7.0841,-4.52263,-0.26677,1.65386,0.17949,2.74405,-0.3027,2.18862,-0.14368,2.10733,0.21029,1.49705,-1.23627,-0.19302,-0.4924,-1.94044,-1.0054,-1.28841,-0.24621,-0.97022,0,0,0.15903,-0.04172,-0.5847,-3.64092,-0.06659,-3.60439],"curve":[0.25,0,0.75,1]},{"time":0.6666,"vertices":[-0.77456,-2.38382,0,0,-0.53345,-2.10213,-1.93898,-3.63051,-6.51472,-2.94734,-7.96143,0.70921,-8.36663,-0.2193,-13.83636,2.95898,-14.07092,-1.30962,-8.42302,-2.44661,-4.18587,-0.45391,-3.16499,-2.44648,0,0,0,0,0,0,0.73864,2.91063,0,0,0,0,0,0,0,0,0,0,0,0,0,0,0,0,-0.64117,-0.52161,-1.33364,-2.58204,-1.2722,0.3338,0,0,-0.0308,1.21537,-1.5441,1.26748,-1.13357,-2.46207,-1.14384,-3.83916,-0.85657,-2.70725,-2.90332,-4.75724,-2.26214,-4.23563,-2.30827,-5.08585,0,0,-14.17356,0.95942,-13.09705,-3.44258,-9.16163,-5.35727,-7.0841,-4.52263,-0.26677,1.65386,0.17949,2.74405,-0.3027,2.18862,-0.14368,2.10733,0.21029,1.49705,-1.23627,-0.19302,-0.4924,-1.94044,-1.0054,-1.28841,-0.24621,-0.97022,0,0,0.15903,-0.04172,-0.5847,-3.64092,-0.06659,-3.60439],"curve":[0.25,0,0.75,1]},{"time":0.8333,"vertices":[-0.77456,-2.38382,0,0,-0.53345,-2.10213,-1.93898,-3.63051,-8.5915,-2.13757,-4.66272,-2.97825,-1.91698,-5.31574,-3.73897,3.5073,-6.44981,2.67291,-5.78429,-2.89644,-3.66883,-0.75683,-3.16499,-2.44648,0,0,0,0,0,0,0.73864,2.91063,0,0,0,0,0,0,0,0,0,0,0,0,0,0,0,0,-0.64117,-0.52161,-1.33364,-2.58204,-1.2722,0.3338,0,0,-0.0308,1.21537,-1.5441,1.26748,-1.13357,-2.46207,-1.14384,-3.83916,-0.85657,-2.70725,-1.51807,-4.34898,-2.26214,-4.23563,-2.30827,-5.08585,0,0,-8.44081,1.31294,-10.49211,-1.75813,-7.58708,-3.41807,-7.0841,-4.52263,-0.26677,1.65386,0.17949,2.74405,-0.3027,2.18862,-0.14368,2.10733,0.21029,1.49705,-1.23627,-0.19302,-0.4924,-1.94044,-1.0054,-1.28841,-0.24621,-0.97022,0,0,0.15903,-0.04172,-0.5847,-3.64092,-0.06659,-3.60439],"curve":[0.25,0,0.75,1]},{"time":1,"vertices":[-0.77456,-2.38382,0,0,-0.53345,-2.10213,-1.93898,-3.63051,-6.51472,-2.94734,-7.96143,0.70921,-8.36663,-0.2193,-13.83636,2.95898,-14.07092,-1.30962,-8.42302,-2.44661,-4.18587,-0.45391,-3.16499,-2.44648,0,0,0,0,0,0,0.73864,2.91063,0,0,0,0,0,0,0,0,0,0,0,0,0,0,0,0,-0.64117,-0.52161,-1.33364,-2.58204,-1.2722,0.3338,0,0,-0.0308,1.21537,-1.5441,1.26748,-1.13357,-2.46207,-1.14384,-3.83916,-0.85657,-2.70725,-2.90332,-4.75724,-2.26214,-4.23563,-2.30827,-5.08585,0,0,-14.17356,0.95942,-13.09705,-3.44258,-9.16163,-5.35727,-7.0841,-4.52263,-0.26677,1.65386,0.17949,2.74405,-0.3027,2.18862,-0.14368,2.10733,0.21029,1.49705,-1.23627,-0.19302,-0.4924,-1.94044,-1.0054,-1.28841,-0.24621,-0.97022,0,0,0.15903,-0.04172,-0.5847,-3.64092,-0.06659,-3.60439],"curve":[0.25,0,0.75,1]},{"time":1.1666,"vertices":[-0.77456,-2.38382,0,0,-0.53345,-2.10213,-1.93898,-3.63051,-8.5915,-2.13757,-4.66272,-2.97825,-1.91698,-5.31574,-3.73897,3.5073,-6.44981,2.67291,-5.78429,-2.89644,-3.66883,-0.75683,-3.16499,-2.44648,0,0,0,0,0,0,0.73864,2.91063,0,0,0,0,0,0,0,0,0,0,0,0,0,0,0,0,-0.64117,-0.52161,-1.33364,-2.58204,-1.2722,0.3338,0,0,-0.0308,1.21537,-1.5441,1.26748,-1.13357,-2.46207,-1.14384,-3.83916,-0.85657,-2.70725,-1.51807,-4.34898,-2.26214,-4.23563,-2.30827,-5.08585,0,0,-8.44081,1.31294,-10.49211,-1.75813,-7.58708,-3.41807,-7.0841,-4.52263,-0.26677,1.65386,0.17949,2.74405,-0.3027,2.18862,-0.14368,2.10733,0.21029,1.49705,-1.23627,-0.19302,-0.4924,-1.94044,-1.0054,-1.28841,-0.24621,-0.97022,0,0,0.15903,-0.04172,-0.5847,-3.64092,-0.06659,-3.60439],"curve":[0.25,0,0.75,1]},{"time":1.3333,"vertices":[-0.77456,-2.38382,0,0,-0.53345,-2.10213,-1.93898,-3.63051,-6.51472,-2.94734,-7.96143,0.70921,-8.36663,-0.2193,-13.83636,2.95898,-14.07092,-1.30962,-8.42302,-2.44661,-4.18587,-0.45391,-3.16499,-2.44648,0,0,0,0,0,0,0.73864,2.91063,0,0,0,0,0,0,0,0,0,0,0,0,0,0,0,0,-0.64117,-0.52161,-1.33364,-2.58204,-1.2722,0.3338,0,0,-0.0308,1.21537,-1.5441,1.26748,-1.13357,-2.46207,-1.14384,-3.83916,-0.85657,-2.70725,-2.90332,-4.75724,-2.26214,-4.23563,-2.30827,-5.08585,0,0,-14.17356,0.95942,-13.09705,-3.44258,-9.16163,-5.35727,-7.0841,-4.52263,-0.26677,1.65386,0.17949,2.74405,-0.3027,2.18862,-0.14368,2.10733,0.21029,1.49705,-1.23627,-0.19302,-0.4924,-1.94044,-1.0054,-1.28841,-0.24621,-0.97022,0,0,0.15903,-0.04172,-0.5847,-3.64092,-0.06659,-3.60439],"curve":[0.25,0,0.75,1]},{"time":1.6666}]},"common_squirrel_earth_acc_2":{"common_squirrel_earth_acc_02":[{"time":0,"curve":"stepped"},{"time":0.3333,"curve":"stepped"},{"time":1.3333,"curve":"stepped"},{"time":1.6666}]},"common_squirrel_earth_body_2":{"common_squirrel_earth_body_01":[{"time":0,"offset":4,"vertices":[-1.16438,-2.19264,0.31402,2.14815],"curve":[0.25,0,0.75,1]},{"time":0.3333,"curve":"stepped"},{"time":1.3333,"curve":[0.25,0,0.75,1]},{"time":1.6666,"offset":4,"vertices":[-1.16438,-2.19264,0.31402,2.14815]}]},"common_squirrel_earth_tail_2":{"common_squirrel_earth_tail_01":[{"time":0,"curve":"stepped"},{"time":0.3333,"curve":"stepped"},{"time":1.3333,"curve":"stepped"},{"time":1.6666}]}}},"drawOrder":[{"time":0,"offsets":[{"slot":"common_squirrel_earth_acc_2","offset":-5}]},{"time":0.0333,"offsets":[{"slot":"common_squirrel_earth_acc_2","offset":-16}]},{"time":0.3333,"offsets":[{"slot":"common_squirrel_earth_arm_4","offset":19}]},{"time":0.5,"offsets":[{"slot":"common_squirrel_earth_arm_4","offset":19}]},{"time":0.6666,"offsets":[{"slot":"common_squirrel_earth_arm_4","offset":19}]},{"time":0.8333,"offsets":[{"slot":"common_squirrel_earth_arm_4","offset":19}]},{"time":1,"offsets":[{"slot":"common_squirrel_earth_arm_4","offset":19}]},{"time":1.1666,"offsets":[{"slot":"common_squirrel_earth_arm_4","offset":19}]},{"time":1.3333,"offsets":[{"slot":"common_squirrel_earth_arm_4","offset":19}]},{"time":1.4,"offsets":[{"slot":"common_squirrel_earth_acc_2","offset":-16}]},{"time":1.6666,"offsets":[{"slot":"common_squirrel_earth_acc_2","offset":-5}]}]},"skill_1_appear":{"slots":{"bone4":{"attachment":[{"time":0,"name":"common_squirrel_earth_leg_01"},{"time":0.3333,"name":"common_squirrel_earth_leg_01"}]},"bone7":{"attachment":[{"time":0,"name":null},{"time":0.3333,"name":null}]},"bone8":{"attachment":[{"time":0,"name":"common_squirrel_earth_head_01"},{"time":0.3333,"name":"common_squirrel_earth_head_01"}]},"bone10":{"attachment":[{"time":0,"name":"common_squirrel_earth_weapon_01"},{"time":0.3333,"name":"common_squirrel_earth_weapon_01"}],"color":[{"time":0,"color":"ffffffff","curve":[0.25,0,0.75,1]},{"time":0.1666,"color":"ffffff00","curve":"stepped"},{"time":0.3333,"color":"ffffff00"}]},"common_squirrel_earth_acc_01":{"attachment":[{"time":0,"name":"common_squirrel_earth_acc_01"},{"time":0.3333,"name":"common_squirrel_earth_acc_01"}]},"common_squirrel_earth_acc_2":{"attachment":[{"time":0,"name":"common_squirrel_earth_acc_02"},{"time":0.3333,"name":"common_squirrel_earth_acc_02"}],"color":[{"time":0,"color":"ffffffff","curve":[0.25,0,0.75,1]},{"time":0.1666,"color":"ffffff00","curve":"stepped"},{"time":0.3333,"color":"ffffff00"}]},"common_squirrel_earth_arm_1":{"attachment":[{"time":0,"name":null},{"time":0.3333,"name":null}]},"common_squirrel_earth_arm_01":{"attachment":[{"time":0,"name":null},{"time":0.3333,"name":null}]},"common_squirrel_earth_arm_2":{"attachment":[{"time":0,"name":null},{"time":0.3333,"name":null}]},"common_squirrel_earth_arm_3":{"attachment":[{"time":0,"name":"common_squirrel_earth_arm_01"},{"time":0.3333,"name":"common_squirrel_earth_arm_01"}],"color":[{"time":0,"color":"ffffffff","curve":"stepped"},{"time":0.1666,"color":"ffffffff","curve":[0.25,0,0.75,1]},{"time":0.3333,"color":"ffffff00"}]},"common_squirrel_earth_arm_4":{"attachment":[{"time":0,"name":"common_squirrel_earth_arm_02"},{"time":0.3333,"name":"common_squirrel_earth_arm_02"}]},"common_squirrel_earth_arm_5":{"attachment":[{"time":0,"name":"common_squirrel_earth_arm_02"},{"time":0.3333,"name":"common_squirrel_earth_arm_02"}],"color":[{"time":0,"color":"ffffff00","curve":"stepped"},{"time":0.1666,"color":"ffffff00","curve":[0.25,0,0.75,1]},{"time":0.3333,"color":"ffffffff"}]},"common_squirrel_earth_body_1":{"attachment":[{"time":0,"name":null},{"time":0.3333,"name":null}]},"common_squirrel_earth_body_01":{"attachment":[{"time":0,"name":null},{"time":0.3333,"name":null}]},"common_squirrel_earth_body_2":{"attachment":[{"time":0,"name":"common_squirrel_earth_body_01"},{"time":0.3333,"name":"common_squirrel_earth_body_01"}]},"common_squirrel_earth_head_1":{"attachment":[{"time":0,"name":null},{"time":0.3333,"name":null}]},"common_squirrel_earth_head_2":{"attachment":[{"time":0,"name":"common_squirrel_earth_head_02"},{"time":0.3333,"name":"common_squirrel_earth_head_02"}]},"common_squirrel_earth_leg_1":{"attachment":[{"time":0,"name":null},{"time":0.3333,"name":null}]},"common_squirrel_earth_leg_01":{"attachment":[{"time":0,"name":null},{"time":0.3333,"name":null}]},"common_squirrel_earth_leg_2":{"attachment":[{"time":0,"name":null},{"time":0.3333,"name":null}]},"common_squirrel_earth_leg_3":{"attachment":[{"time":0,"name":null},{"time":0.3333,"name":null}]},"common_squirrel_earth_leg_4":{"attachment":[{"time":0,"name":"common_squirrel_earth_leg_02"},{"time":0.3333,"name":"common_squirrel_earth_leg_02"}]},"common_squirrel_earth_tail_1":{"attachment":[{"time":0,"name":null},{"time":0.3333,"name":null}]},"common_squirrel_earth_tail_2":{"attachment":[{"time":0,"name":"common_squirrel_earth_tail_01"},{"time":0.3333,"name":"common_squirrel_earth_tail_01"}]}},"bones":{"bone":{"rotate":[{"time":0,"angle":-12,"curve":"stepped"},{"time":0.3333,"angle":-12}],"translate":[{"time":0,"x":0,"y":0,"curve":"stepped"},{"time":0.3333,"x":0,"y":0}],"scale":[{"time":0,"x":1,"y":1,"curve":"stepped"},{"time":0.3333,"x":1,"y":1}]},"bone10":{"rotate":[{"time":0,"angle":27.33,"curve":[0.25,0,0.75,1]},{"time":0.1666,"angle":96.27,"curve":[0.25,0,0.75,1]},{"time":0.3333,"angle":87.3}],"translate":[{"time":0,"x":0,"y":0,"curve":"stepped"},{"time":0.3333,"x":0,"y":0}],"scale":[{"time":0,"x":1,"y":1,"curve":"stepped"},{"time":0.3333,"x":1,"y":1}]},"bone7":{"rotate":[{"time":0,"angle":5.89,"curve":"stepped"},{"time":0.3333,"angle":5.89}],"translate":[{"time":0,"x":-2.28,"y":0.44,"curve":"stepped"},{"time":0.3333,"x":-2.28,"y":0.44}],"scale":[{"time":0,"x":1,"y":1,"curve":"stepped"},{"time":0.3333,"x":1,"y":1}]},"bone4":{"rotate":[{"time":0,"angle":0,"curve":"stepped"},{"time":0.3333,"angle":0}],"translate":[{"time":0,"x":0,"y":0,"curve":"stepped"},{"time":0.3333,"x":0,"y":0}],"scale":[{"time":0,"x":1,"y":1,"curve":"stepped"},{"time":0.3333,"x":1,"y":1}]},"bone6":{"rotate":[{"time":0,"angle":-61.41,"curve":"stepped"},{"time":0.3333,"angle":-61.41}],"translate":[{"time":0,"x":-1.24,"y":6.18,"curve":"stepped"},{"time":0.3333,"x":-1.24,"y":6.18}],"scale":[{"time":0,"x":1,"y":1,"curve":"stepped"},{"time":0.3333,"x":1,"y":1}]},"bone8":{"rotate":[{"time":0,"angle":-24.45,"curve":"stepped"},{"time":0.3333,"angle":-24.45}],"translate":[{"time":0,"x":0,"y":0,"curve":"stepped"},{"time":0.3333,"x":0,"y":0}],"scale":[{"time":0,"x":1,"y":1,"curve":"stepped"},{"time":0.3333,"x":1,"y":1}]},"bone9":{"rotate":[{"time":0,"angle":0,"curve":"stepped"},{"time":0.3333,"angle":0}],"translate":[{"time":0,"x":0,"y":0,"curve":"stepped"},{"time":0.3333,"x":0,"y":0}],"scale":[{"time":0,"x":1,"y":1,"curve":"stepped"},{"time":0.3333,"x":1,"y":1}]},"bone3":{"rotate":[{"time":0,"angle":46.12,"curve":[0.25,0,0.75,1]},{"time":0.3333,"angle":-230.05}],"translate":[{"time":0,"x":-1.74,"y":1.33,"curve":[0.25,0,0.75,1]},{"time":0.3333,"x":-3.82,"y":0.41}],"scale":[{"time":0,"x":1,"y":1,"curve":[0.25,0,0.75,1]},{"time":0.3333,"x":1.289,"y":1}]},"bone5":{"rotate":[{"time":0,"angle":-26.1,"curve":[0.25,0,0.75,1]},{"time":0.1666,"angle":42.83,"curve":[0.25,0,0.75,1]},{"time":0.3333,"angle":249.53}],"translate":[{"time":0,"x":-2.94,"y":2.23,"curve":[0.25,0,0.75,1]},{"time":0.1666,"x":-2.64,"y":4.25,"curve":[0.25,0,0.75,1]},{"time":0.3333,"x":-3,"y":-2.32}],"scale":[{"time":0,"x":1,"y":1,"curve":[0.25,0,0.75,1]},{"time":0.3333,"x":1.268,"y":1}]},"bone11":{"rotate":[{"time":0,"angle":0,"curve":[0.25,0,0.75,1]},{"time":0.3333,"angle":-30.7}],"translate":[{"time":0,"x":0,"y":0,"curve":[0.25,0,0.75,1]},{"time":0.3333,"x":-1.22,"y":2.94}],"scale":[{"time":0,"x":1,"y":1,"curve":"stepped"},{"time":0.3333,"x":1,"y":1}]},"bone2":{"rotate":[{"time":0,"angle":0,"curve":"stepped"},{"time":0.3333,"angle":0}],"translate":[{"time":0,"x":0,"y":0,"curve":"stepped"},{"time":0.3333,"x":0,"y":0}],"scale":[{"time":0,"x":1,"y":1,"curve":[0.25,0,0.75,1]},{"time":0.1666,"x":1.156,"y":1,"curve":[0.25,0,0.75,1]},{"time":0.3333,"x":1,"y":1}]},"bone12":{"rotate":[{"time":0,"angle":0,"curve":"stepped"},{"time":0.3333,"angle":0}],"translate":[{"time":0,"x":0,"y":0,"curve":[0.25,0,0.75,1]},{"time":0.3333,"x":0.97,"y":0.59}],"scale":[{"time":0,"x":1,"y":1,"curve":"stepped"},{"time":0.3333,"x":1,"y":1}]},"root":{"rotate":[{"time":0,"angle":0,"curve":"stepped"},{"time":0.3333,"angle":0}],"translate":[{"time":0,"x":0,"y":0,"curve":"stepped"},{"time":0.3333,"x":0,"y":0}],"scale":[{"time":0,"x":1,"y":1,"curve":"stepped"},{"time":0.3333,"x":1,"y":1}]},"bone13":{"rotate":[{"time":0,"angle":0,"curve":"stepped"},{"time":0.3333,"angle":0}],"translate":[{"time":0,"x":0,"y":0,"curve":"stepped"},{"time":0.3333,"x":0,"y":0}],"scale":[{"time":0,"x":1,"y":1,"curve":"stepped"},{"time":0.3333,"x":1,"y":1}]}},"ffd":{"default":{"bone8":{"common_squirrel_earth_head_01":[{"time":0,"curve":[0.25,0,0.75,1]},{"time":0.3333,"vertices":[-0.77456,-2.38382,0,0,-0.53345,-2.10213,-1.93898,-3.63051,-6.51472,-2.94734,-7.96143,0.70921,-8.36663,-0.2193,-13.83636,2.95898,-14.07092,-1.30962,-8.42302,-2.44661,-4.18587,-0.45391,-3.16499,-2.44648,0,0,0,0,0,0,0.73864,2.91063,0,0,0,0,0,0,0,0,0,0,0,0,0,0,0,0,-0.64117,-0.52161,-1.33364,-2.58204,-1.2722,0.3338,0,0,-0.0308,1.21537,-1.5441,1.26748,-1.13357,-2.46207,-1.14384,-3.83916,-0.85657,-2.70725,-2.90332,-4.75724,-2.26214,-4.23563,-2.30827,-5.08585,0,0,-14.17356,0.95942,-13.09705,-3.44258,-9.16163,-5.35727,-7.0841,-4.52263,-0.26677,1.65386,0.17949,2.74405,-0.3027,2.18862,-0.14368,2.10733,0.21029,1.49705,-1.23627,-0.19302,-0.4924,-1.94044,-1.0054,-1.28841,-0.24621,-0.97022,0,0,0.15903,-0.04172,-0.5847,-3.64092,-0.06659,-3.60439]}]},"common_squirrel_earth_acc_2":{"common_squirrel_earth_acc_02":[{"time":0,"curve":"stepped"},{"time":0.3333}]},"common_squirrel_earth_body_2":{"common_squirrel_earth_body_01":[{"time":0,"offset":4,"vertices":[-1.16438,-2.19264,0.31402,2.14815],"curve":[0.25,0,0.75,1]},{"time":0.3333}]},"common_squirrel_earth_tail_2":{"common_squirrel_earth_tail_01":[{"time":0,"curve":"stepped"},{"time":0.3333}]}}},"drawOrder":[{"time":0,"offsets":[{"slot":"common_squirrel_earth_acc_2","offset":-5}]},{"time":0.0333,"offsets":[{"slot":"common_squirrel_earth_acc_2","offset":-16}]},{"time":0.3333,"offsets":[{"slot":"common_squirrel_earth_arm_4","offset":19}]}]},"skill_1_disappear":{"slots":{"bone4":{"attachment":[{"time":0,"name":"common_squirrel_earth_leg_01"},{"time":0.3333,"name":"common_squirrel_earth_leg_01"}]},"bone7":{"attachment":[{"time":0,"name":null},{"time":0.3333,"name":null}]},"bone8":{"attachment":[{"time":0,"name":"common_squirrel_earth_head_01"},{"time":0.3333,"name":"common_squirrel_earth_head_01"}]},"bone10":{"attachment":[{"time":0,"name":"common_squirrel_earth_weapon_01"},{"time":0.3333,"name":"common_squirrel_earth_weapon_01"}],"color":[{"time":0,"color":"ffffff00","curve":"stepped"},{"time":0.2333,"color":"ffffff00","curve":[0.25,0,0.75,1]},{"time":0.3333,"color":"ffffffff"}]},"common_squirrel_earth_acc_01":{"attachment":[{"time":0,"name":"common_squirrel_earth_acc_01"},{"time":0.3333,"name":"common_squirrel_earth_acc_01"}]},"common_squirrel_earth_acc_2":{"attachment":[{"time":0,"name":"common_squirrel_earth_acc_02"},{"time":0.3333,"name":"common_squirrel_earth_acc_02"}],"color":[{"time":0,"color":"ffffff00","curve":"stepped"},{"time":0.2333,"color":"ffffff00","curve":[0.25,0,0.75,1]},{"time":0.3333,"color":"ffffffff"}]},"common_squirrel_earth_arm_01":{"attachment":[{"time":0,"name":null},{"time":0.3333,"name":null}]},"common_squirrel_earth_arm_1":{"attachment":[{"time":0,"name":null},{"time":0.3333,"name":null}]},"common_squirrel_earth_arm_2":{"attachment":[{"time":0,"name":null},{"time":0.3333,"name":null}]},"common_squirrel_earth_arm_3":{"attachment":[{"time":0,"name":"common_squirrel_earth_arm_01"},{"time":0.3333,"name":"common_squirrel_earth_arm_01"}],"color":[{"time":0,"color":"ffffff00","curve":"stepped"},{"time":0.1666,"color":"ffffff00","curve":[0.25,0,0.75,1]},{"time":0.3333,"color":"ffffffff"}]},"common_squirrel_earth_arm_4":{"attachment":[{"time":0,"name":"common_squirrel_earth_arm_02"},{"time":0.3333,"name":"common_squirrel_earth_arm_02"}]},"common_squirrel_earth_arm_5":{"attachment":[{"time":0,"name":"common_squirrel_earth_arm_02"},{"time":0.3333,"name":"common_squirrel_earth_arm_02"}],"color":[{"time":0,"color":"ffffffff","curve":"stepped"},{"time":0.1666,"color":"ffffffff","curve":[0.25,0,0.75,1]},{"time":0.3333,"color":"ffffff00"}]},"common_squirrel_earth_body_01":{"attachment":[{"time":0,"name":null},{"time":0.3333,"name":null}]},"common_squirrel_earth_body_1":{"attachment":[{"time":0,"name":null},{"time":0.3333,"name":null}]},"common_squirrel_earth_body_2":{"attachment":[{"time":0,"name":"common_squirrel_earth_body_01"},{"time":0.3333,"name":"common_squirrel_earth_body_01"}]},"common_squirrel_earth_head_1":{"attachment":[{"time":0,"name":null},{"time":0.3333,"name":null}]},"common_squirrel_earth_head_2":{"attachment":[{"time":0,"name":"common_squirrel_earth_head_02"},{"time":0.3333,"name":"common_squirrel_earth_head_02"}]},"common_squirrel_earth_leg_01":{"attachment":[{"time":0,"name":null},{"time":0.3333,"name":null}]},"common_squirrel_earth_leg_1":{"attachment":[{"time":0,"name":null},{"time":0.3333,"name":null}]},"common_squirrel_earth_leg_2":{"attachment":[{"time":0,"name":null},{"time":0.3333,"name":null}]},"common_squirrel_earth_leg_3":{"attachment":[{"time":0,"name":null},{"time":0.3333,"name":null}]},"common_squirrel_earth_leg_4":{"attachment":[{"time":0,"name":"common_squirrel_earth_leg_02"},{"time":0.3333,"name":"common_squirrel_earth_leg_02"}]},"common_squirrel_earth_tail_1":{"attachment":[{"time":0,"name":null},{"time":0.3333,"name":null}]},"common_squirrel_earth_tail_2":{"attachment":[{"time":0,"name":"common_squirrel_earth_tail_01"},{"time":0.3333,"name":"common_squirrel_earth_tail_01"}]}},"bones":{"bone11":{"rotate":[{"time":0,"angle":-30.7,"curve":[0.25,0,0.75,1]},{"time":0.3333,"angle":0}],"translate":[{"time":0,"x":-1.22,"y":2.94,"curve":[0.25,0,0.75,1]},{"time":0.3333,"x":0,"y":0}],"scale":[{"time":0,"x":1,"y":1,"curve":"stepped"},{"time":0.3333,"x":1,"y":1}]},"root":{"rotate":[{"time":0,"angle":0,"curve":"stepped"},{"time":0.3333,"angle":0}],"translate":[{"time":0,"x":0,"y":0,"curve":"stepped"},{"time":0.3333,"x":0,"y":0}],"scale":[{"time":0,"x":1,"y":1,"curve":"stepped"},{"time":0.3333,"x":1,"y":1}]},"bone3":{"rotate":[{"time":0,"angle":-230.05,"curve":[0.25,0,0.75,1]},{"time":0.3333,"angle":46.12}],"translate":[{"time":0,"x":-3.82,"y":0.41,"curve":[0.25,0,0.75,1]},{"time":0.3333,"x":-1.74,"y":1.33}],"scale":[{"time":0,"x":1.289,"y":1,"curve":[0.25,0,0.75,1]},{"time":0.3333,"x":1,"y":1}]},"bone6":{"rotate":[{"time":0,"angle":-61.41,"curve":"stepped"},{"time":0.3333,"angle":-61.41}],"translate":[{"time":0,"x":-1.24,"y":6.18,"curve":"stepped"},{"time":0.3333,"x":-1.24,"y":6.18}],"scale":[{"time":0,"x":1,"y":1,"curve":"stepped"},{"time":0.3333,"x":1,"y":1}]},"bone4":{"rotate":[{"time":0,"angle":0,"curve":"stepped"},{"time":0.3333,"angle":0}],"translate":[{"time":0,"x":0,"y":0,"curve":"stepped"},{"time":0.3333,"x":0,"y":0}],"scale":[{"time":0,"x":1,"y":1,"curve":"stepped"},{"time":0.3333,"x":1,"y":1}]},"bone5":{"rotate":[{"time":0,"angle":249.53,"curve":[0.25,0,0.75,1]},{"time":0.1666,"angle":42.83,"curve":[0.25,0,0.75,1]},{"time":0.3333,"angle":-26.1}],"translate":[{"time":0,"x":-3,"y":-2.32,"curve":[0.25,0,0.75,1]},{"time":0.1666,"x":-2.64,"y":4.25,"curve":[0.25,0,0.75,1]},{"time":0.3333,"x":-2.94,"y":2.23}],"scale":[{"time":0,"x":1.268,"y":1,"curve":[0.25,0,0.75,1]},{"time":0.3333,"x":1,"y":1}]},"bone13":{"rotate":[{"time":0,"angle":0,"curve":"stepped"},{"time":0.3333,"angle":0}],"translate":[{"time":0,"x":0,"y":0,"curve":"stepped"},{"time":0.3333,"x":0,"y":0}],"scale":[{"time":0,"x":1,"y":1,"curve":"stepped"},{"time":0.3333,"x":1,"y":1}]},"bone7":{"rotate":[{"time":0,"angle":5.89,"curve":"stepped"},{"time":0.3333,"angle":5.89}],"translate":[{"time":0,"x":-2.28,"y":0.44,"curve":"stepped"},{"time":0.3333,"x":-2.28,"y":0.44}],"scale":[{"time":0,"x":1,"y":1,"curve":"stepped"},{"time":0.3333,"x":1,"y":1}]},"bone10":{"rotate":[{"time":0,"angle":87.3,"curve":[0.25,0,0.75,1]},{"time":0.1666,"angle":96.27,"curve":[0.25,0,0.75,1]},{"time":0.3333,"angle":27.33}],"translate":[{"time":0,"x":0,"y":0,"curve":"stepped"},{"time":0.3333,"x":0,"y":0}],"scale":[{"time":0,"x":1,"y":1,"curve":"stepped"},{"time":0.3333,"x":1,"y":1}]},"bone8":{"rotate":[{"time":0,"angle":-24.45,"curve":"stepped"},{"time":0.3333,"angle":-24.45}],"translate":[{"time":0,"x":0,"y":0,"curve":"stepped"},{"time":0.3333,"x":0,"y":0}],"scale":[{"time":0,"x":1,"y":1,"curve":"stepped"},{"time":0.3333,"x":1,"y":1}]},"bone2":{"rotate":[{"time":0,"angle":0,"curve":"stepped"},{"time":0.3333,"angle":0}],"translate":[{"time":0,"x":0,"y":0,"curve":"stepped"},{"time":0.3333,"x":0,"y":0}],"scale":[{"time":0,"x":1,"y":1,"curve":[0.25,0,0.75,1]},{"time":0.1666,"x":1.156,"y":1,"curve":[0.25,0,0.75,1]},{"time":0.3333,"x":1,"y":1}]},"bone9":{"rotate":[{"time":0,"angle":0,"curve":"stepped"},{"time":0.3333,"angle":0}],"translate":[{"time":0,"x":0,"y":0,"curve":"stepped"},{"time":0.3333,"x":0,"y":0}],"scale":[{"time":0,"x":1,"y":1,"curve":"stepped"},{"time":0.3333,"x":1,"y":1}]},"bone":{"rotate":[{"time":0,"angle":-12,"curve":"stepped"},{"time":0.3333,"angle":-12}],"translate":[{"time":0,"x":0,"y":0,"curve":"stepped"},{"time":0.3333,"x":0,"y":0}],"scale":[{"time":0,"x":1,"y":1,"curve":"stepped"},{"time":0.3333,"x":1,"y":1}]},"bone12":{"rotate":[{"time":0,"angle":0,"curve":"stepped"},{"time":0.3333,"angle":0}],"translate":[{"time":0,"x":0.97,"y":0.59,"curve":[0.25,0,0.75,1]},{"time":0.3333,"x":0,"y":0}],"scale":[{"time":0,"x":1,"y":1,"curve":"stepped"},{"time":0.3333,"x":1,"y":1}]}},"ffd":{"default":{"bone8":{"common_squirrel_earth_head_01":[{"time":0,"vertices":[-0.77456,-2.38382,0,0,-0.53345,-2.10213,-1.93898,-3.63051,-6.51472,-2.94734,-7.96143,0.70921,-8.36663,-0.2193,-13.83636,2.95898,-14.07092,-1.30962,-8.42302,-2.44661,-4.18587,-0.45391,-3.16499,-2.44648,0,0,0,0,0,0,0.73864,2.91063,0,0,0,0,0,0,0,0,0,0,0,0,0,0,0,0,-0.64117,-0.52161,-1.33364,-2.58204,-1.2722,0.3338,0,0,-0.0308,1.21537,-1.5441,1.26748,-1.13357,-2.46207,-1.14384,-3.83916,-0.85657,-2.70725,-2.90332,-4.75724,-2.26214,-4.23563,-2.30827,-5.08585,0,0,-14.17356,0.95942,-13.09705,-3.44258,-9.16163,-5.35727,-7.0841,-4.52263,-0.26677,1.65386,0.17949,2.74405,-0.3027,2.18862,-0.14368,2.10733,0.21029,1.49705,-1.23627,-0.19302,-0.4924,-1.94044,-1.0054,-1.28841,-0.24621,-0.97022,0,0,0.15903,-0.04172,-0.5847,-3.64092,-0.06659,-3.60439],"curve":[0.25,0,0.75,1]},{"time":0.3333}]},"common_squirrel_earth_acc_2":{"common_squirrel_earth_acc_02":[{"time":0,"curve":"stepped"},{"time":0.3333}]},"common_squirrel_earth_body_2":{"common_squirrel_earth_body_01":[{"time":0,"curve":[0.25,0,0.75,1]},{"time":0.3333,"offset":4,"vertices":[-1.16438,-2.19264,0.31402,2.14815]}]},"common_squirrel_earth_tail_2":{"common_squirrel_earth_tail_01":[{"time":0,"curve":"stepped"},{"time":0.3333}]}}},"drawOrder":[{"time":0,"offsets":[{"slot":"common_squirrel_earth_arm_4","offset":19}]},{"time":0.0666,"offsets":[{"slot":"common_squirrel_earth_acc_2","offset":-16}]},{"time":0.3333,"offsets":[{"slot":"common_squirrel_earth_acc_2","offset":-5}]}]},"skill_1_idle":{"slots":{"bone4":{"attachment":[{"time":0,"name":"common_squirrel_earth_leg_01"},{"time":1,"name":"common_squirrel_earth_leg_01"}]},"bone7":{"attachment":[{"time":0,"name":null},{"time":1,"name":null}]},"bone8":{"attachment":[{"time":0,"name":"common_squirrel_earth_head_01"},{"time":1,"name":"common_squirrel_earth_head_01"}]},"bone10":{"attachment":[{"time":0,"name":"common_squirrel_earth_weapon_01"},{"time":1,"name":"common_squirrel_earth_weapon_01"}],"color":[{"time":0,"color":"ffffff00","curve":"stepped"},{"time":1,"color":"ffffff00"}]},"common_squirrel_earth_acc_01":{"attachment":[{"time":0,"name":"common_squirrel_earth_acc_01"},{"time":1,"name":"common_squirrel_earth_acc_01"}]},"common_squirrel_earth_acc_2":{"attachment":[{"time":0,"name":"common_squirrel_earth_acc_02"},{"time":1,"name":"common_squirrel_earth_acc_02"}],"color":[{"time":0,"color":"ffffff00","curve":"stepped"},{"time":1,"color":"ffffff00"}]},"common_squirrel_earth_arm_1":{"attachment":[{"time":0,"name":null},{"time":1,"name":null}]},"common_squirrel_earth_arm_01":{"attachment":[{"time":0,"name":null},{"time":1,"name":null}]},"common_squirrel_earth_arm_2":{"attachment":[{"time":0,"name":null},{"time":1,"name":null}]},"common_squirrel_earth_arm_3":{"attachment":[{"time":0,"name":"common_squirrel_earth_arm_01"},{"time":1,"name":"common_squirrel_earth_arm_01"}],"color":[{"time":0,"color":"ffffff00","curve":"stepped"},{"time":0.1666,"color":"ffffff00","curve":"stepped"},{"time":0.3333,"color":"ffffff00","curve":"stepped"},{"time":0.5,"color":"ffffff00","curve":"stepped"},{"time":0.6666,"color":"ffffff00","curve":"stepped"},{"time":0.8333,"color":"ffffff00","curve":"stepped"},{"time":1,"color":"ffffff00"}]},"common_squirrel_earth_arm_4":{"attachment":[{"time":0,"name":"common_squirrel_earth_arm_02"},{"time":1,"name":"common_squirrel_earth_arm_02"}]},"common_squirrel_earth_arm_5":{"attachment":[{"time":0,"name":"common_squirrel_earth_arm_02"},{"time":1,"name":"common_squirrel_earth_arm_02"}],"color":[{"time":0,"color":"ffffffff","curve":"stepped"},{"time":0.1666,"color":"ffffffff","curve":"stepped"},{"time":0.3333,"color":"ffffffff","curve":"stepped"},{"time":0.5,"color":"ffffffff","curve":"stepped"},{"time":0.6666,"color":"ffffffff","curve":"stepped"},{"time":0.8333,"color":"ffffffff","curve":"stepped"},{"time":1,"color":"ffffffff"}]},"common_squirrel_earth_body_01":{"attachment":[{"time":0,"name":null},{"time":1,"name":null}]},"common_squirrel_earth_body_1":{"attachment":[{"time":0,"name":null},{"time":1,"name":null}]},"common_squirrel_earth_body_2":{"attachment":[{"time":0,"name":"common_squirrel_earth_body_01"},{"time":1,"name":"common_squirrel_earth_body_01"}]},"common_squirrel_earth_head_1":{"attachment":[{"time":0,"name":null},{"time":1,"name":null}]},"common_squirrel_earth_head_2":{"attachment":[{"time":0,"name":"common_squirrel_earth_head_02"},{"time":1,"name":"common_squirrel_earth_head_02"}]},"common_squirrel_earth_leg_1":{"attachment":[{"time":0,"name":null},{"time":1,"name":null}]},"common_squirrel_earth_leg_01":{"attachment":[{"time":0,"name":null},{"time":1,"name":null}]},"common_squirrel_earth_leg_2":{"attachment":[{"time":0,"name":null},{"time":1,"name":null}]},"common_squirrel_earth_leg_3":{"attachment":[{"time":0,"name":null},{"time":1,"name":null}]},"common_squirrel_earth_leg_4":{"attachment":[{"time":0,"name":"common_squirrel_earth_leg_02"},{"time":1,"name":"common_squirrel_earth_leg_02"}]},"common_squirrel_earth_tail_1":{"attachment":[{"time":0,"name":null},{"time":1,"name":null}]},"common_squirrel_earth_tail_2":{"attachment":[{"time":0,"name":"common_squirrel_earth_tail_01"},{"time":1,"name":"common_squirrel_earth_tail_01"}]}},"bones":{"bone6":{"rotate":[{"time":0,"angle":-61.41,"curve":"stepped"},{"time":1,"angle":-61.41}],"translate":[{"time":0,"x":-1.24,"y":6.18,"curve":"stepped"},{"time":1,"x":-1.24,"y":6.18}],"scale":[{"time":0,"x":1,"y":1,"curve":[0.368,0.47,0.753,1]},{"time":0.1666,"x":0.884,"y":1.026,"curve":[0.368,0.47,0.753,1]},{"time":0.3333,"x":1,"y":1,"curve":[0.368,0.47,0.753,1]},{"time":0.5,"x":0.884,"y":1.026,"curve":[0.368,0.47,0.753,1]},{"time":0.6666,"x":1,"y":1,"curve":[0.368,0.47,0.753,1]},{"time":0.8333,"x":0.884,"y":1.026,"curve":[0.332,0.33,0.667,0.66]},{"time":0.8666,"x":0.914,"y":1.019,"curve":[0.379,0.52,0.746,1]},{"time":1,"x":1,"y":1}]},"bone4":{"rotate":[{"time":0,"angle":0,"curve":"stepped"},{"time":1,"angle":0}],"translate":[{"time":0,"x":0,"y":0,"curve":"stepped"},{"time":1,"x":0,"y":0}],"scale":[{"time":0,"x":1,"y":1,"curve":[0.368,0.47,0.753,1]},{"time":0.1666,"x":0.884,"y":1.026,"curve":[0.368,0.47,0.753,1]},{"time":0.3333,"x":1,"y":1,"curve":[0.368,0.47,0.753,1]},{"time":0.5,"x":0.884,"y":1.026,"curve":[0.368,0.47,0.753,1]},{"time":0.6666,"x":1,"y":1,"curve":[0.368,0.47,0.753,1]},{"time":0.8333,"x":0.884,"y":1.026,"curve":[0.332,0.33,0.667,0.66]},{"time":0.8666,"x":0.914,"y":1.019,"curve":[0.379,0.52,0.746,1]},{"time":1,"x":1,"y":1}]},"bone13":{"rotate":[{"time":0,"angle":0,"curve":"stepped"},{"time":1,"angle":0}],"translate":[{"time":0,"x":0,"y":0,"curve":"stepped"},{"time":1,"x":0,"y":0}],"scale":[{"time":0,"x":1,"y":1,"curve":"stepped"},{"time":1,"x":1,"y":1}]},"bone10":{"rotate":[{"time":0,"angle":87.3,"curve":"stepped"},{"time":1,"angle":87.3}],"translate":[{"time":0,"x":0,"y":0,"curve":"stepped"},{"time":1,"x":0,"y":0}],"scale":[{"time":0,"x":1,"y":1,"curve":"stepped"},{"time":1,"x":1,"y":1}]},"bone7":{"rotate":[{"time":0,"angle":5.89,"curve":"stepped"},{"time":1,"angle":5.89}],"translate":[{"time":0,"x":-2.28,"y":0.44,"curve":"stepped"},{"time":1,"x":-2.28,"y":0.44}],"scale":[{"time":0,"x":1,"y":1,"curve":"stepped"},{"time":1,"x":1,"y":1}]},"bone3":{"rotate":[{"time":0,"angle":-230.05,"curve":"stepped"},{"time":1,"angle":-230.05}],"translate":[{"time":0,"x":-3.82,"y":0.41,"curve":"stepped"},{"time":1,"x":-3.82,"y":0.41}],"scale":[{"time":0,"x":1.289,"y":1,"curve":[0.283,0.11,0.629,0.5]},{"time":0.1666,"x":1,"y":1,"curve":[0.283,0.11,0.629,0.5]},{"time":0.3333,"x":1.289,"y":1,"curve":[0.283,0.11,0.629,0.5]},{"time":0.5,"x":1,"y":1,"curve":[0.283,0.11,0.629,0.5]},{"time":0.6666,"x":1.289,"y":1,"curve":[0.283,0.11,0.629,0.5]},{"time":0.8333,"x":1,"y":1,"curve":[0.319,0.22,0.653,0.56]},{"time":0.8666,"x":1.034,"y":1,"curve":[0.298,0.19,0.64,0.56]},{"time":1,"x":1.289,"y":1}]},"bone9":{"rotate":[{"time":0,"angle":0,"curve":"stepped"},{"time":1,"angle":0}],"translate":[{"time":0,"x":0,"y":0,"curve":"stepped"},{"time":1,"x":0,"y":0}],"scale":[{"time":0,"x":1,"y":1,"curve":"stepped"},{"time":1,"x":1,"y":1}]},"bone5":{"rotate":[{"time":0,"angle":249.53,"curve":"stepped"},{"time":1,"angle":249.53}],"translate":[{"time":0,"x":-3,"y":-2.32,"curve":"stepped"},{"time":1,"x":-3,"y":-2.32}],"scale":[{"time":0,"x":1.268,"y":1,"curve":[0.361,0.64,0.697,1]},{"time":0.0333,"x":1.294,"y":1,"curve":[0.368,0.47,0.753,1]},{"time":0.2,"x":1,"y":1,"curve":[0.368,0.47,0.753,1]},{"time":0.3666,"x":1.294,"y":1,"curve":[0.368,0.47,0.753,1]},{"time":0.5333,"x":1,"y":1,"curve":[0.368,0.47,0.753,1]},{"time":0.7,"x":1.294,"y":1,"curve":[0.368,0.47,0.753,1]},{"time":0.8666,"x":1,"y":1,"curve":[0.352,0.39,0.717,0.84]},{"time":1,"x":1.268,"y":1}]},"bone8":{"rotate":[{"time":0,"angle":-24.45,"curve":"stepped"},{"time":1,"angle":-24.45}],"translate":[{"time":0,"x":0,"y":0,"curve":"stepped"},{"time":1,"x":0,"y":0}],"scale":[{"time":0,"x":1,"y":1,"curve":"stepped"},{"time":1,"x":1,"y":1}]},"root":{"rotate":[{"time":0,"angle":0,"curve":"stepped"},{"time":1,"angle":0}],"translate":[{"time":0,"x":0,"y":0,"curve":"stepped"},{"time":1,"x":0,"y":0}],"scale":[{"time":0,"x":1,"y":1,"curve":"stepped"},{"time":1,"x":1,"y":1}]},"bone2":{"rotate":[{"time":0,"angle":0,"curve":"stepped"},{"time":1,"angle":0}],"translate":[{"time":0,"x":0,"y":0,"curve":"stepped"},{"time":1,"x":0,"y":0}],"scale":[{"time":0,"x":1,"y":1,"curve":[0.25,0,0.75,1]},{"time":0.1666,"x":1.13,"y":0.974,"curve":[0.25,0,0.75,1]},{"time":0.3333,"x":1,"y":1,"curve":[0.25,0,0.75,1]},{"time":0.5,"x":1.13,"y":0.974,"curve":[0.25,0,0.75,1]},{"time":0.6666,"x":1,"y":1,"curve":[0.25,0,0.75,1]},{"time":0.8333,"x":1.13,"y":0.974,"curve":[0.284,0,0.625,0.38]},{"time":0.8666,"x":1.113,"y":0.977,"curve":[0.32,0.28,0.757,1]},{"time":1,"x":1,"y":1}]},"bone":{"rotate":[{"time":0,"angle":-12,"curve":"stepped"},{"time":1,"angle":-12}],"translate":[{"time":0,"x":0,"y":0,"curve":"stepped"},{"time":1,"x":0,"y":0}],"scale":[{"time":0,"x":1,"y":1,"curve":"stepped"},{"time":1,"x":1,"y":1}]},"bone11":{"rotate":[{"time":0,"angle":-30.7,"curve":[0.25,0,0.75,1]},{"time":0.1666,"angle":0,"curve":[0.25,0,0.75,1]},{"time":0.3333,"angle":-30.7,"curve":[0.25,0,0.75,1]},{"time":0.5,"angle":0,"curve":[0.25,0,0.75,1]},{"time":0.6666,"angle":-30.7,"curve":[0.25,0,0.75,1]},{"time":0.8333,"angle":0,"curve":[0.25,0,0.75,1]},{"time":1,"angle":-30.7}],"translate":[{"time":0,"x":-1.22,"y":2.94,"curve":[0.25,0,0.75,1]},{"time":0.1666,"x":0,"y":0,"curve":[0.25,0,0.75,1]},{"time":0.3333,"x":-1.22,"y":2.94,"curve":[0.25,0,0.75,1]},{"time":0.5,"x":0,"y":0,"curve":[0.25,0,0.75,1]},{"time":0.6666,"x":-1.22,"y":2.94,"curve":[0.25,0,0.75,1]},{"time":0.8333,"x":0,"y":0,"curve":[0.25,0,0.75,1]},{"time":1,"x":-1.22,"y":2.94}],"scale":[{"time":0,"x":1,"y":1,"curve":"stepped"},{"time":1,"x":1,"y":1}]},"bone12":{"rotate":[{"time":0,"angle":0,"curve":"stepped"},{"time":1,"angle":0}],"translate":[{"time":0,"x":0.97,"y":0.59,"curve":"stepped"},{"time":1,"x":0.97,"y":0.59}],"scale":[{"time":0,"x":1,"y":1,"curve":"stepped"},{"time":1,"x":1,"y":1}]}},"ffd":{"default":{"bone8":{"common_squirrel_earth_head_01":[{"time":0,"vertices":[-0.77456,-2.38382,0,0,-0.53345,-2.10213,-1.93898,-3.63051,-6.51472,-2.94734,-7.96143,0.70921,-8.36663,-0.2193,-13.83636,2.95898,-14.07092,-1.30962,-8.42302,-2.44661,-4.18587,-0.45391,-3.16499,-2.44648,0,0,0,0,0,0,0.73864,2.91063,0,0,0,0,0,0,0,0,0,0,0,0,0,0,0,0,-0.64117,-0.52161,-1.33364,-2.58204,-1.2722,0.3338,0,0,-0.0308,1.21537,-1.5441,1.26748,-1.13357,-2.46207,-1.14384,-3.83916,-0.85657,-2.70725,-2.90332,-4.75724,-2.26214,-4.23563,-2.30827,-5.08585,0,0,-14.17356,0.95942,-13.09705,-3.44258,-9.16163,-5.35727,-7.0841,-4.52263,-0.26677,1.65386,0.17949,2.74405,-0.3027,2.18862,-0.14368,2.10733,0.21029,1.49705,-1.23627,-0.19302,-0.4924,-1.94044,-1.0054,-1.28841,-0.24621,-0.97022,0,0,0.15903,-0.04172,-0.5847,-3.64092,-0.06659,-3.60439],"curve":[0.25,0,0.75,1]},{"time":0.1666,"vertices":[-0.77456,-2.38382,0,0,-0.53345,-2.10213,-1.93898,-3.63051,-8.5915,-2.13757,-4.66272,-2.97825,-1.91698,-5.31574,-3.73897,3.5073,-6.44981,2.67291,-5.78429,-2.89644,-2.56221,-0.94547,-0.68747,-0.73791,0,0,0,0,0,0,0.73864,2.91063,0,0,0,0,0,0,0,0,0,0,0,0,0,0,0,0,-0.64117,-0.52161,-1.33364,-2.58204,-1.2722,0.3338,0,0,-0.0308,1.21537,-1.5441,1.26748,-1.13357,-2.46207,-1.14384,-3.83916,-0.85657,-2.70725,-1.51807,-4.34898,-2.26214,-4.23563,-2.30827,-5.08585,0,0,-8.44081,1.31294,-10.49211,-1.75813,-7.58708,-3.41807,-4.60658,-2.81406,-0.26677,1.65386,0.17949,2.74405,-0.3027,2.18862,-0.14368,2.10733,0.21029,1.49705,-1.23627,-0.19302,-0.4924,-1.94044,-1.0054,-1.28841,-0.24621,-0.97022,0,0,0.15903,-0.04172,-0.5847,-3.64092,-0.06659,-3.60439],"curve":[0.25,0,0.75,1]},{"time":0.3333,"vertices":[-0.77456,-2.38382,0,0,-0.53345,-2.10213,-1.93898,-3.63051,-6.51472,-2.94734,-7.96143,0.70921,-8.36663,-0.2193,-13.83636,2.95898,-14.07092,-1.30962,-8.42302,-2.44661,-4.18587,-0.45391,-3.16499,-2.44648,0,0,0,0,0,0,0.73864,2.91063,0,0,0,0,0,0,0,0,0,0,0,0,0,0,0,0,-0.64117,-0.52161,-1.33364,-2.58204,-1.2722,0.3338,0,0,-0.0308,1.21537,-1.5441,1.26748,-1.13357,-2.46207,-1.14384,-3.83916,-0.85657,-2.70725,-2.90332,-4.75724,-2.26214,-4.23563,-2.30827,-5.08585,0,0,-14.17356,0.95942,-13.09705,-3.44258,-9.16163,-5.35727,-7.0841,-4.52263,-0.26677,1.65386,0.17949,2.74405,-0.3027,2.18862,-0.14368,2.10733,0.21029,1.49705,-1.23627,-0.19302,-0.4924,-1.94044,-1.0054,-1.28841,-0.24621,-0.97022,0,0,0.15903,-0.04172,-0.5847,-3.64092,-0.06659,-3.60439],"curve":[0.25,0,0.75,1]},{"time":0.5,"vertices":[-0.77456,-2.38382,0,0,-0.53345,-2.10213,-1.93898,-3.63051,-8.5915,-2.13757,-4.66272,-2.97825,-1.91698,-5.31574,-3.73897,3.5073,-6.44981,2.67291,-5.78429,-2.89644,-2.56221,-0.94547,-0.68747,-0.73791,0,0,0,0,0,0,0.73864,2.91063,0,0,0,0,0,0,0,0,0,0,0,0,0,0,0,0,-0.64117,-0.52161,-1.33364,-2.58204,-1.2722,0.3338,0,0,-0.0308,1.21537,-1.5441,1.26748,-1.13357,-2.46207,-1.14384,-3.83916,-0.85657,-2.70725,-1.51807,-4.34898,-2.26214,-4.23563,-2.30827,-5.08585,0,0,-8.44081,1.31294,-10.49211,-1.75813,-7.58708,-3.41807,-4.60658,-2.81406,-0.26677,1.65386,0.17949,2.74405,-0.3027,2.18862,-0.14368,2.10733,0.21029,1.49705,-1.23627,-0.19302,-0.4924,-1.94044,-1.0054,-1.28841,-0.24621,-0.97022,0,0,0.15903,-0.04172,-0.5847,-3.64092,-0.06659,-3.60439],"curve":[0.25,0,0.75,1]},{"time":0.6666,"vertices":[-0.77456,-2.38382,0,0,-0.53345,-2.10213,-1.93898,-3.63051,-6.51472,-2.94734,-7.96143,0.70921,-8.36663,-0.2193,-13.83636,2.95898,-14.07092,-1.30962,-8.42302,-2.44661,-4.18587,-0.45391,-3.16499,-2.44648,0,0,0,0,0,0,0.73864,2.91063,0,0,0,0,0,0,0,0,0,0,0,0,0,0,0,0,-0.64117,-0.52161,-1.33364,-2.58204,-1.2722,0.3338,0,0,-0.0308,1.21537,-1.5441,1.26748,-1.13357,-2.46207,-1.14384,-3.83916,-0.85657,-2.70725,-2.90332,-4.75724,-2.26214,-4.23563,-2.30827,-5.08585,0,0,-14.17356,0.95942,-13.09705,-3.44258,-9.16163,-5.35727,-7.0841,-4.52263,-0.26677,1.65386,0.17949,2.74405,-0.3027,2.18862,-0.14368,2.10733,0.21029,1.49705,-1.23627,-0.19302,-0.4924,-1.94044,-1.0054,-1.28841,-0.24621,-0.97022,0,0,0.15903,-0.04172,-0.5847,-3.64092,-0.06659,-3.60439],"curve":[0.25,0,0.75,1]},{"time":0.8333,"vertices":[-0.77456,-2.38382,0,0,-0.53345,-2.10213,-1.93898,-3.63051,-8.5915,-2.13757,-4.66272,-2.97825,-1.91698,-5.31574,-3.73897,3.5073,-6.44981,2.67291,-5.78429,-2.89644,-2.56221,-0.94547,-0.68747,-0.73791,0,0,0,0,0,0,0.73864,2.91063,0,0,0,0,0,0,0,0,0,0,0,0,0,0,0,0,-0.64117,-0.52161,-1.33364,-2.58204,-1.2722,0.3338,0,0,-0.0308,1.21537,-1.5441,1.26748,-1.13357,-2.46207,-1.14384,-3.83916,-0.85657,-2.70725,-1.51807,-4.34898,-2.26214,-4.23563,-2.30827,-5.08585,0,0,-8.44081,1.31294,-10.49211,-1.75813,-7.58708,-3.41807,-4.60658,-2.81406,-0.26677,1.65386,0.17949,2.74405,-0.3027,2.18862,-0.14368,2.10733,0.21029,1.49705,-1.23627,-0.19302,-0.4924,-1.94044,-1.0054,-1.28841,-0.24621,-0.97022,0,0,0.15903,-0.04172,-0.5847,-3.64092,-0.06659,-3.60439],"curve":[0.25,0,0.75,1]},{"time":1,"vertices":[-0.77456,-2.38382,0,0,-0.53345,-2.10213,-1.93898,-3.63051,-6.51472,-2.94734,-7.96143,0.70921,-8.36663,-0.2193,-13.83636,2.95898,-14.07092,-1.30962,-8.42302,-2.44661,-4.18587,-0.45391,-3.16499,-2.44648,0,0,0,0,0,0,0.73864,2.91063,0,0,0,0,0,0,0,0,0,0,0,0,0,0,0,0,-0.64117,-0.52161,-1.33364,-2.58204,-1.2722,0.3338,0,0,-0.0308,1.21537,-1.5441,1.26748,-1.13357,-2.46207,-1.14384,-3.83916,-0.85657,-2.70725,-2.90332,-4.75724,-2.26214,-4.23563,-2.30827,-5.08585,0,0,-14.17356,0.95942,-13.09705,-3.44258,-9.16163,-5.35727,-7.0841,-4.52263,-0.26677,1.65386,0.17949,2.74405,-0.3027,2.18862,-0.14368,2.10733,0.21029,1.49705,-1.23627,-0.19302,-0.4924,-1.94044,-1.0054,-1.28841,-0.24621,-0.97022,0,0,0.15903,-0.04172,-0.5847,-3.64092,-0.06659,-3.60439]}]},"common_squirrel_earth_acc_2":{"common_squirrel_earth_acc_02":[{"time":0,"curve":"stepped"},{"time":1}]},"common_squirrel_earth_body_2":{"common_squirrel_earth_body_01":[{"time":0,"curve":"stepped"},{"time":1}]},"common_squirrel_earth_tail_2":{"common_squirrel_earth_tail_01":[{"time":0,"curve":"stepped"},{"time":1}]}}},"drawOrder":[{"time":0,"offsets":[{"slot":"common_squirrel_earth_arm_4","offset":19}]},{"time":0.1666,"offsets":[{"slot":"common_squirrel_earth_arm_4","offset":19}]},{"time":0.3333,"offsets":[{"slot":"common_squirrel_earth_arm_4","offset":19}]},{"time":0.5,"offsets":[{"slot":"common_squirrel_earth_arm_4","offset":19}]},{"time":0.6666,"offsets":[{"slot":"common_squirrel_earth_arm_4","offset":19}]},{"time":0.8333,"offsets":[{"slot":"common_squirrel_earth_arm_4","offset":19}]},{"time":1,"offsets":[{"slot":"common_squirrel_earth_arm_4","offset":19}]}]}}}